Workbook

Sheet RETURN MASTER
A1: Column1 | B1: Date | C1: Transaction type | D1: Number | E1: Customer full name | F1: Memo/Description | G1: Quantity | H1: Sales price | I1: Amount | J1: Balance | K1: Line
A2: 128 LM LAWN | K2: {=_xlfn.LET(_xlpm.d,UPPER(TRIM(CLEAN(SUBSTITUTE(F2,CHAR(160)," ")))),_xlpm.keys,UPPER(TRIM(MAP!$B$1:$B$401)),_xlpm.vals,MAP!$A$1:$A$401,_xlpm.matchlen,IF(ISNUMBER(SEARCH(_xlpm.keys,_xlpm.d)),LEN(_xlpm.keys),0),_xlpm.best,MAX(_xlpm.matchlen),IF(_xlpm.best=0,"",INDEX(_xlpm.vals,MATCH(_xlpm.best,_xlpm.matchlen,0))))}
B3: 45786 | C3: Credit Note | D3: 26571 | E3: LIFESTYLE HOME GARDEN | F3: 128 LM LAWN | G3: -10 | H3: 69.95 | I3: -699.5 | J3: -699.5 | K3: {=_xlfn.LET(_xlpm.d,UPPER(TRIM(CLEAN(SUBSTITUTE(F3,CHAR(160)," ")))),_xlpm.keys,UPPER(TRIM(MAP!$B$1:$B$401)),_xlpm.vals,MAP!$A$1:$A$401,_xlpm.matchlen,IF(ISNUMBER(SEARCH(_xlpm.keys,_xlpm.d)),LEN(_xlpm.keys),0),_xlpm.best,MAX(_xlpm.matchlen),IF(_xlpm.best=0,"",INDEX(_xlpm.vals,MATCH(_xlpm.best,_xlpm.matchlen,0))))} -> LAWN PLUGS
B4: 46029 | C4: Credit Note | D4: 16060 | E4: GARDENSHOP PARKTOWN | F4: 128 LM LAWN | G4: -6 | H4: 124.3 | I4: -745.8 | J4: -1445.3 | K4: {=_xlfn.LET(_xlpm.d,UPPER(TRIM(CLEAN(SUBSTITUTE(F4,CHAR(160)," ")))),_xlpm.keys,UPPER(TRIM(MAP!$B$1:$B$401)),_xlpm.vals,MAP!$A$1:$A$401,_xlpm.matchlen,IF(ISNUMBER(SEARCH(_xlpm.keys,_xlpm.d)),LEN(_xlpm.keys),0),_xlpm.best,MAX(_xlpm.matchlen),IF(_xlpm.best=0,"",INDEX(_xlpm.vals,MATCH(_xlpm.best,_xlpm.matchlen,0))))} -> LAWN PLUGS
A5: Total for 128 LM LAWN | G5: -16 | I5: =I3+I4 -> -1445.3 | K5: {=_xlfn.LET(_xlpm.d,UPPER(TRIM(CLEAN(SUBSTITUTE(F5,CHAR(160)," ")))),_xlpm.keys,UPPER(TRIM(MAP!$B$1:$B$401)),_xlpm.vals,MAP!$A$1:$A$401,_xlpm.matchlen,IF(ISNUMBER(SEARCH(_xlpm.keys,_xlpm.d)),LEN(_xlpm.keys),0),_xlpm.best,MAX(_xlpm.matchlen),IF(_xlpm.best=0,"",INDEX(_xlpm.vals,MATCH(_xlpm.best,_xlpm.matchlen,0))))}
A6: AT LAWN PLUG SEEDLINGS 128 | K6: {=_xlfn.LET(_xlpm.d,UPPER(TRIM(CLEAN(SUBSTITUTE(F6,CHAR(160)," ")))),_xlpm.keys,UPPER(TRIM(MAP!$B$1:$B$401)),_xlpm.vals,MAP!$A$1:$A$401,_xlpm.matchlen,IF(ISNUMBER(SEARCH(_xlpm.keys,_xlpm.d)),LEN(_xlpm.keys),0),_xlpm.best,MAX(_xlpm.matchlen),IF(_xlpm.best=0,"",INDEX(_xlpm.vals,MATCH(_xlpm.best,_xlpm.matchlen,0))))}
B7: 46070 | C7: Credit Note | D7: 4401602785 | E7: BUILDERS WAREHOUSE:RIVONIA | F7: AT LAWN PLUG SEEDLINGS 128 850040203 | G7: -1 | H7: 126.35 | I7: -126.35 | J7: -126.35 | K7: {=_xlfn.LET(_xlpm.d,UPPER(TRIM(CLEAN(SUBSTITUTE(F7,CHAR(160)," ")))),_xlpm.keys,UPPER(TRIM(MAP!$B$1:$B$401)),_xlpm.vals,MAP!$A$1:$A$401,_xlpm.matchlen,IF(ISNUMBER(SEARCH(_xlpm.keys,_xlpm.d)),LEN(_xlpm.keys),0),_xlpm.best,MAX(_xlpm.matchlen),IF(_xlpm.best=0,"",INDEX(_xlpm.vals,MATCH(_xlpm.best,_xlpm.matchlen,0))))} -> LAWN PLUGS
A8: Total for AT LAWN PLUG SEEDLINGS 128 | G8: -1 | I8: =I7 -> -126.35 | K8: {=_xlfn.LET(_xlpm.d,UPPER(TRIM(CLEAN(SUBSTITUTE(F8,CHAR(160)," ")))),_xlpm.keys,UPPER(TRIM(MAP!$B$1:$B$401)),_xlpm.vals,MAP!$A$1:$A$401,_xlpm.matchlen,IF(ISNUMBER(SEARCH(_xlpm.keys,_xlpm.d)),LEN(_xlpm.keys),0),_xlpm.best,MAX(_xlpm.matchlen),IF(_xlpm.best=0,"",INDEX(_xlpm.vals,MATCH(_xlpm.best,_xlpm.matchlen,0))))}
A9: AT HYPOESTES POT 12CM | K9: {=_xlfn.LET(_xlpm.d,UPPER(TRIM(CLEAN(SUBSTITUTE(F9,CHAR(160)," ")))),_xlpm.keys,UPPER(TRIM(MAP!$B$1:$B$401)),_xlpm.vals,MAP!$A$1:$A$401,_xlpm.matchlen,IF(ISNUMBER(SEARCH(_xlpm.keys,_xlpm.d)),LEN(_xlpm.keys),0),_xlpm.best,MAX(_xlpm.matchlen),IF(_xlpm.best=0,"",INDEX(_xlpm.vals,MATCH(_xlpm.best,_xlpm.matchlen,0))))}
B10: 46063 | C10: Credit Note | D10: 4401600447 | E10: BUILDERS WAREHOUSE:ERASMUS PARK | F10: AT HYPOESTES POT 12CM 850040155 | G10: -8 | H10: 12.2 | I10: -97.6 | J10: -97.6 | K10: {=_xlfn.LET(_xlpm.d,UPPER(TRIM(CLEAN(SUBSTITUTE(F10,CHAR(160)," ")))),_xlpm.keys,UPPER(TRIM(MAP!$B$1:$B$401)),_xlpm.vals,MAP!$A$1:$A$401,_xlpm.matchlen,IF(ISNUMBER(SEARCH(_xlpm.keys,_xlpm.d)),LEN(_xlpm.keys),0),_xlpm.best,MAX(_xlpm.matchlen),IF(_xlpm.best=0,"",INDEX(_xlpm.vals,MATCH(_xlpm.best,_xlpm.matchlen,0))))} -> 12CM COLOUR POT
A11: Total for AT HYPOESTES POT 12CM | G11: -8 | I11: =I10 -> -97.6 | K11: {=_xlfn.LET(_xlpm.d,UPPER(TRIM(CLEAN(SUBSTITUTE(F11,CHAR(160)," ")))),_xlpm.keys,UPPER(TRIM(MAP!$B$1:$B$401)),_xlpm.vals,MAP!$A$1:$A$401,_xlpm.matchlen,IF(ISNUMBER(SEARCH(_xlpm.keys,_xlpm.d)),LEN(_xlpm.keys),0),_xlpm.best,MAX(_xlpm.matchlen),IF(_xlpm.best=0,"",INDEX(_xlpm.vals,MATCH(_xlpm.best,_xlpm.matchlen,0))))}
A12: AT IMPATIENS POT 12CM | K12: {=_xlfn.LET(_xlpm.d,UPPER(TRIM(CLEAN(SUBSTITUTE(F12,CHAR(160)," ")))),_xlpm.keys,UPPER(TRIM(MAP!$B$1:$B$401)),_xlpm.vals,MAP!$A$1:$A$401,_xlpm.matchlen,IF(ISNUMBER(SEARCH(_xlpm.keys,_xlpm.d)),LEN(_xlpm.keys),0),_xlpm.best,MAX(_xlpm.matchlen),IF(_xlpm.best=0,"",INDEX(_xlpm.vals,MATCH(_xlpm.best,_xlpm.matchlen,0))))}
B13: 46079 | C13: Credit Note | D13: 4401605618 | E13: BUILDERS WAREHOUSE:KEMPTON PARK | F13: AT IMPATIENS POT 12CM 850040109 | G13: -25 | H13: 12.2 | I13: -305 | J13: -305 | K13: {=_xlfn.LET(_xlpm.d,UPPER(TRIM(CLEAN(SUBSTITUTE(F13,CHAR(160)," ")))),_xlpm.keys,UPPER(TRIM(MAP!$B$1:$B$401)),_xlpm.vals,MAP!$A$1:$A$401,_xlpm.matchlen,IF(ISNUMBER(SEARCH(_xlpm.keys,_xlpm.d)),LEN(_xlpm.keys),0),_xlpm.best,MAX(_xlpm.matchlen),IF(_xlpm.best=0,"",INDEX(_xlpm.vals,MATCH(_xlpm.best,_xlpm.matchlen,0))))} -> 12CM COLOUR POT
A14: Total for AT IMPATIENS POT 12CM | G14: -25 | I14: =I13 -> -305 | K14: {=_xlfn.LET(_xlpm.d,UPPER(TRIM(CLEAN(SUBSTITUTE(F14,CHAR(160)," ")))),_xlpm.keys,UPPER(TRIM(MAP!$B$1:$B$401)),_xlpm.vals,MAP!$A$1:$A$401,_xlpm.matchlen,IF(ISNUMBER(SEARCH(_xlpm.keys,_xlpm.d)),LEN(_xlpm.keys),0),_xlpm.best,MAX(_xlpm.matchlen),IF(_xlpm.best=0,"",INDEX(_xlpm.vals,MATCH(_xlpm.best,_xlpm.matchlen,0))))}
A15: AT PETUNIA HYBRIDS POT 12CM | K15: {=_xlfn.LET(_xlpm.d,UPPER(TRIM(CLEAN(SUBSTITUTE(F15,CHAR(160)," ")))),_xlpm.keys,UPPER(TRIM(MAP!$B$1:$B$401)),_xlpm.vals,MAP!$A$1:$A$401,_xlpm.matchlen,IF(ISNUMBER(SEARCH(_xlpm.keys,_xlpm.d)),LEN(_xlpm.keys),0),_xlpm.best,MAX(_xlpm.matchlen),IF(_xlpm.best=0,"",INDEX(_xlpm.vals,MATCH(_xlpm.best,_xlpm.matchlen,0))))}
B16: 46027 | C16: Credit Note | D16: 89764A | E16: BUILDERS WAREHOUSE:NEWMARKET | F16: AT PETUNIA HYBRIDS POT 12CM 850040146 | G16: -30 | H16: 27.95 | I16: -838.5 | J16: -838.5 | K16: {=_xlfn.LET(_xlpm.d,UPPER(TRIM(CLEAN(SUBSTITUTE(F16,CHAR(160)," ")))),_xlpm.keys,UPPER(TRIM(MAP!$B$1:$B$401)),_xlpm.vals,MAP!$A$1:$A$401,_xlpm.matchlen,IF(ISNUMBER(SEARCH(_xlpm.keys,_xlpm.d)),LEN(_xlpm.keys),0),_xlpm.best,MAX(_xlpm.matchlen),IF(_xlpm.best=0,"",INDEX(_xlpm.vals,MATCH(_xlpm.best,_xlpm.matchlen,0))))} -> 12CM PETUNIA HYBRIDS
B17: 46028 | C17: Credit Note | D17: 89772A | E17: BUILDERS WAREHOUSE:SILVERLAKES | F17: AT PETUNIA HYBRIDS POT 12CM 850040146 | G17: -2 | H17: 27.95 | I17: -55.9 | J17: -894.4 | K17: {=_xlfn.LET(_xlpm.d,UPPER(TRIM(CLEAN(SUBSTITUTE(F17,CHAR(160)," ")))),_xlpm.keys,UPPER(TRIM(MAP!$B$1:$B$401)),_xlpm.vals,MAP!$A$1:$A$401,_xlpm.matchlen,IF(ISNUMBER(SEARCH(_xlpm.keys,_xlpm.d)),LEN(_xlpm.keys),0),_xlpm.best,MAX(_xlpm.matchlen),IF(_xlpm.best=0,"",INDEX(_xlpm.vals,MATCH(_xlpm.best,_xlpm.matchlen,0))))} -> 12CM PETUNIA HYBRIDS
B18: 46035 | C18: Credit Note | D18: 4401592795 | E18: BUILDERS WAREHOUSE:ZAMBEZI | F18: AT PETUNIA HYBRIDS POT 12CM 850040146 | G18: -5 | H18: 27.95 | I18: -139.75 | J18: -1034.15 | K18: {=_xlfn.LET(_xlpm.d,UPPER(TRIM(CLEAN(SUBSTITUTE(F18,CHAR(160)," ")))),_xlpm.keys,UPPER(TRIM(MAP!$B$1:$B$401)),_xlpm.vals,MAP!$A$1:$A$401,_xlpm.matchlen,IF(ISNUMBER(SEARCH(_xlpm.keys,_xlpm.d)),LEN(_xlpm.keys),0),_xlpm.best,MAX(_xlpm.matchlen),IF(_xlpm.best=0,"",INDEX(_xlpm.vals,MATCH(_xlpm.best,_xlpm.matchlen,0))))} -> 12CM PETUNIA HYBRIDS
B19: 46049 | C19: Credit Note | D19: 4401596213 | E19: BUILDERS WAREHOUSE:ZAMBEZI | F19: AT PETUNIA HYBRIDS POT 12CM 850040146 | G19: -4 | H19: 27.95 | I19: -111.8 | J19: -1145.95 | K19: {=_xlfn.LET(_xlpm.d,UPPER(TRIM(CLEAN(SUBSTITUTE(F19,CHAR(160)," ")))),_xlpm.keys,UPPER(TRIM(MAP!$B$1:$B$401)),_xlpm.vals,MAP!$A$1:$A$401,_xlpm.matchlen,IF(ISNUMBER(SEARCH(_xlpm.keys,_xlpm.d)),LEN(_xlpm.keys),0),_xlpm.best,MAX(_xlpm.matchlen),IF(_xlpm.best=0,"",INDEX(_xlpm.vals,MATCH(_xlpm.best,_xlpm.matchlen,0))))} -> 12CM PETUNIA HYBRIDS
B20: 46056 | C20: Credit Note | D20: 4401598139 | E20: BUILDERS WAREHOUSE:LYNNWOOD | F20: AT PETUNIA HYBRIDS POT 12CM 850040146 | G20: -10 | H20: 27.95 | I20: -279.5 | J20: -1425.45 | K20: {=_xlfn.LET(_xlpm.d,UPPER(TRIM(CLEAN(SUBSTITUTE(F20,CHAR(160)," ")))),_xlpm.keys,UPPER(TRIM(MAP!$B$1:$B$401)),_xlpm.vals,MAP!$A$1:$A$401,_xlpm.matchlen,IF(ISNUMBER(SEARCH(_xlpm.keys,_xlpm.d)),LEN(_xlpm.keys),0),_xlpm.best,MAX(_xlpm.matchlen),IF(_xlpm.best=0,"",INDEX(_xlpm.vals,MATCH(_xlpm.best,_xlpm.matchlen,0))))} -> 12CM PETUNIA HYBRIDS
B21: 46066 | C21: Credit Note | D21: 4401601731 | E21: BUILDERS WAREHOUSE:NEWMARKET | F21: AT PETUNIA HYBRIDS POT 12CM 850040146 | G21: -15 | H21: 27.95 | I21: -419.25 | J21: -1844.7 | K21: {=_xlfn.LET(_xlpm.d,UPPER(TRIM(CLEAN(SUBSTITUTE(F21,CHAR(160)," ")))),_xlpm.keys,UPPER(TRIM(MAP!$B$1:$B$401)),_xlpm.vals,MAP!$A$1:$A$401,_xlpm.matchlen,IF(ISNUMBER(SEARCH(_xlpm.keys,_xlpm.d)),LEN(_xlpm.keys),0),_xlpm.best,MAX(_xlpm.matchlen),IF(_xlpm.best=0,"",INDEX(_xlpm.vals,MATCH(_xlpm.best,_xlpm.matchlen,0))))} -> 12CM PETUNIA HYBRIDS
B22: 46070 | C22: Credit Note | D22: 4401602766 | E22: BUILDERS WAREHOUSE:CENTURION | F22: AT PETUNIA HYBRIDS POT 12CM 850040146 | G22: -40 | H22: 27.95 | I22: -1118 | J22: -2962.7 | K22: {=_xlfn.LET(_xlpm.d,UPPER(TRIM(CLEAN(SUBSTITUTE(F22,CHAR(160)," ")))),_xlpm.keys,UPPER(TRIM(MAP!$B$1:$B$401)),_xlpm.vals,MAP!$A$1:$A$401,_xlpm.matchlen,IF(ISNUMBER(SEARCH(_xlpm.keys,_xlpm.d)),LEN(_xlpm.keys),0),_xlpm.best,MAX(_xlpm.matchlen),IF(_xlpm.best=0,"",INDEX(_xlpm.vals,MATCH(_xlpm.best,_xlpm.matchlen,0))))} -> 12CM PETUNIA HYBRIDS
B23: 46071 | C23: Credit Note | D23: 4401603219 | E23: BUILDERS WAREHOUSE:ZAMBEZI | F23: AT PETUNIA HYBRIDS POT 12CM 850040146 | G23: -15 | H23: 27.95 | I23: -419.25 | J23: -3381.95 | K23: {=_xlfn.LET(_xlpm.d,UPPER(TRIM(CLEAN(SUBSTITUTE(F23,CHAR(160)," ")))),_xlpm.keys,UPPER(TRIM(MAP!$B$1:$B$401)),_xlpm.vals,MAP!$A$1:$A$401,_xlpm.matchlen,IF(ISNUMBER(SEARCH(_xlpm.keys,_xlpm.d)),LEN(_xlpm.keys),0),_xlpm.best,MAX(_xlpm.matchlen),IF(_xlpm.best=0,"",INDEX(_xlpm.vals,MATCH(_xlpm.best,_xlpm.matchlen,0))))} -> 12CM PETUNIA HYBRIDS
B24: 46072 | C24: Credit Note | D24: 4401603572 | E24: BUILDERS WAREHOUSE:FLORIDA GLEN | F24: AT PETUNIA HYBRIDS POT 12CM 850040146 | G24: -12 | H24: 27.95 | I24: -335.4 | J24: -3717.35 | K24: {=_xlfn.LET(_xlpm.d,UPPER(TRIM(CLEAN(SUBSTITUTE(F24,CHAR(160)," ")))),_xlpm.keys,UPPER(TRIM(MAP!$B$1:$B$401)),_xlpm.vals,MAP!$A$1:$A$401,_xlpm.matchlen,IF(ISNUMBER(SEARCH(_xlpm.keys,_xlpm.d)),LEN(_xlpm.keys),0),_xlpm.best,MAX(_xlpm.matchlen),IF(_xlpm.best=0,"",INDEX(_xlpm.vals,MATCH(_xlpm.best,_xlpm.matchlen,0))))} -> 12CM PETUNIA HYBRIDS
B25: 46073 | C25: Credit Note | D25: 4401604001 | E25: BUILDERS WAREHOUSE:LAMBTON | F25: AT PETUNIA HYBRIDS POT 12CM 850040146 | G25: -6 | H25: 27.95 | I25: -167.7 | J25: -3885.05 | K25: {=_xlfn.LET(_xlpm.d,UPPER(TRIM(CLEAN(SUBSTITUTE(F25,CHAR(160)," ")))),_xlpm.keys,UPPER(TRIM(MAP!$B$1:$B$401)),_xlpm.vals,MAP!$A$1:$A$401,_xlpm.matchlen,IF(ISNUMBER(SEARCH(_xlpm.keys,_xlpm.d)),LEN(_xlpm.keys),0),_xlpm.best,MAX(_xlpm.matchlen),IF(_xlpm.best=0,"",INDEX(_xlpm.vals,MATCH(_xlpm.best,_xlpm.matchlen,0))))} -> 12CM PETUNIA HYBRIDS
B26: 46077 | C26: Credit Note | D26: 4401604949 | E26: BUILDERS WAREHOUSE:SILVERLAKES | F26: AT PETUNIA HYBRIDS POT 12CM 850040146 | G26: -26 | H26: 27.95 | I26: -726.7 | J26: -4611.75 | K26: {=_xlfn.LET(_xlpm.d,UPPER(TRIM(CLEAN(SUBSTITUTE(F26,CHAR(160)," ")))),_xlpm.keys,UPPER(TRIM(MAP!$B$1:$B$401)),_xlpm.vals,MAP!$A$1:$A$401,_xlpm.matchlen,IF(ISNUMBER(SEARCH(_xlpm.keys,_xlpm.d)),LEN(_xlpm.keys),0),_xlpm.best,MAX(_xlpm.matchlen),IF(_xlpm.best=0,"",INDEX(_xlpm.vals,MATCH(_xlpm.best,_xlpm.matchlen,0))))} -> 12CM PETUNIA HYBRIDS
B27: 46084 | C27: Credit Note | D27: 4401606629 | E27: BUILDERS WAREHOUSE:ZAMBEZI | F27: AT PETUNIA HYBRIDS POT 12CM 850040146 | G27: -8 | H27: 27.95 | I27: -223.6 | J27: -4835.35 | K27: {=_xlfn.LET(_xlpm.d,UPPER(TRIM(CLEAN(SUBSTITUTE(F27,CHAR(160)," ")))),_xlpm.keys,UPPER(TRIM(MAP!$B$1:$B$401)),_xlpm.vals,MAP!$A$1:$A$401,_xlpm.matchlen,IF(ISNUMBER(SEARCH(_xlpm.keys,_xlpm.d)),LEN(_xlpm.keys),0),_xlpm.best,MAX(_xlpm.matchlen),IF(_xlpm.best=0,"",INDEX(_xlpm.vals,MATCH(_xlpm.best,_xlpm.matchlen,0))))} -> 12CM PETUNIA HYBRIDS
... B32: 46112 | C32: Credit Note | D32: 4401615755 | E32: BUILDERS WAREHOUSE:RUSTENBURG | F32: AT PETUNIA HYBRIDS POT 12CM 850040146 | G32: -7 | H32: 27.95 | I32: -195.65 | J32: -6121.05 | K32: {=_xlfn.LET(_xlpm.d,UPPER(TRIM(CLEAN(SUBSTITUTE(F32,CHAR(160)," ")))),_xlpm.keys,UPPER(TRIM(MAP!$B$1:$B$401)),_xlpm.vals,MAP!$A$1:$A$401,_xlpm.matchlen,IF(ISNUMBER(SEARCH(_xlpm.keys,_xlpm.d)),LEN(_xlpm.keys),0),_xlpm.best,MAX(_xlpm.matchlen),IF(_xlpm.best=0,"",INDEX(_xlpm.vals,MATCH(_xlpm.best,_xlpm.matchlen,0))))} -> 12CM PETUNIA HYBRIDS
A33: Total for AT PETUNIA HYBRIDS POT 12CM | G33: -219 | I33: =I16+I17+I18+I19+I20+I21+I22+I23+I24+I25+I26+I27+I28+I29+I30+I31+I32 -> -6121.05 | K33: {=_xlfn.LET(_xlpm.d,UPPER(TRIM(CLEAN(SUBSTITUTE(F33,CHAR(160)," ")))),_xlpm.keys,UPPER(TRIM(MAP!$B$1:$B$401)),_xlpm.vals,MAP!$A$1:$A$401,_xlpm.matchlen,IF(ISNUMBER(SEARCH(_xlpm.keys,_xlpm.d)),LEN(_xlpm.keys),0),_xlpm.best,MAX(_xlpm.matchlen),IF(_xlpm.best=0,"",INDEX(_xlpm.vals,MATCH(_xlpm.best,_xlpm.matchlen,0))))}
A34: AT SEASONAL COLOUR 12CM POT | K34: {=_xlfn.LET(_xlpm.d,UPPER(TRIM(CLEAN(SUBSTITUTE(F34,CHAR(160)," ")))),_xlpm.keys,UPPER(TRIM(MAP!$B$1:$B$401)),_xlpm.vals,MAP!$A$1:$A$401,_xlpm.matchlen,IF(ISNUMBER(SEARCH(_xlpm.keys,_xlpm.d)),LEN(_xlpm.keys),0),_xlpm.best,MAX(_xlpm.matchlen),IF(_xlpm.best=0,"",INDEX(_xlpm.vals,MATCH(_xlpm.best,_xlpm.matchlen,0))))}
B35: 45982 | C35: Credit Note | D35: 89309A | E35: BUILDERS WAREHOUSE:BOKSBURG (NEW) | F35: AT SEASONAL COLOUR 12CM POT 850040171 | G35: -30 | H35: 7 | I35: -210 | J35: -210 | K35: {=_xlfn.LET(_xlpm.d,UPPER(TRIM(CLEAN(SUBSTITUTE(F35,CHAR(160)," ")))),_xlpm.keys,UPPER(TRIM(MAP!$B$1:$B$401)),_xlpm.vals,MAP!$A$1:$A$401,_xlpm.matchlen,IF(ISNUMBER(SEARCH(_xlpm.keys,_xlpm.d)),LEN(_xlpm.keys),0),_xlpm.best,MAX(_xlpm.matchlen),IF(_xlpm.best=0,"",INDEX(_xlpm.vals,MATCH(_xlpm.best,_xlpm.matchlen,0))))} -> 12CM COLOUR POT
B36: 45989 | C36: Credit Note | D36: 89414A | E36: BUILDERS WAREHOUSE:ZAMBEZI | F36: AT SEASONAL COLOUR 12CM POT | G36: -4 | H36: 7 | I36: -28 | J36: -238 | K36: {=_xlfn.LET(_xlpm.d,UPPER(TRIM(CLEAN(SUBSTITUTE(F36,CHAR(160)," ")))),_xlpm.keys,UPPER(TRIM(MAP!$B$1:$B$401)),_xlpm.vals,MAP!$A$1:$A$401,_xlpm.matchlen,IF(ISNUMBER(SEARCH(_xlpm.keys,_xlpm.d)),LEN(_xlpm.keys),0),_xlpm.best,MAX(_xlpm.matchlen),IF(_xlpm.best=0,"",INDEX(_xlpm.vals,MATCH(_xlpm.best,_xlpm.matchlen,0))))} -> 12CM COLOUR POT
B37: 45993 | C37: Credit Note | D37: 4401584725 | E37: BUILDERS WAREHOUSE:RUSTENBURG | F37: AT SEASONAL COLOUR 12CM POT 850040171 | G37: -3 | H37: 7 | I37: -21 | J37: -259 | K37: {=_xlfn.LET(_xlpm.d,UPPER(TRIM(CLEAN(SUBSTITUTE(F37,CHAR(160)," ")))),_xlpm.keys,UPPER(TRIM(MAP!$B$1:$B$401)),_xlpm.vals,MAP!$A$1:$A$401,_xlpm.matchlen,IF(ISNUMBER(SEARCH(_xlpm.keys,_xlpm.d)),LEN(_xlpm.keys),0),_xlpm.best,MAX(_xlpm.matchlen),IF(_xlpm.best=0,"",INDEX(_xlpm.vals,MATCH(_xlpm.best,_xlpm.matchlen,0))))} -> 12CM COLOUR POT
B38: 45994 | C38: Credit Note | D38: 4401585073 | E38: BUILDERS WAREHOUSE:SOUTHGATE | F38: AT SEASONAL COLOUR 12CM POT 850040171 | G38: -19 | H38: 7 | I38: -133 | J38: -392 | K38: {=_xlfn.LET(_xlpm.d,UPPER(TRIM(CLEAN(SUBSTITUTE(F38,CHAR(160)," ")))),_xlpm.keys,UPPER(TRIM(MAP!$B$1:$B$401)),_xlpm.vals,MAP!$A$1:$A$401,_xlpm.matchlen,IF(ISNUMBER(SEARCH(_xlpm.keys,_xlpm.d)),LEN(_xlpm.keys),0),_xlpm.best,MAX(_xlpm.matchlen),IF(_xlpm.best=0,"",INDEX(_xlpm.vals,MATCH(_xlpm.best,_xlpm.matchlen,0))))} -> 12CM COLOUR POT
B39: 45996 | C39: Credit Note | D39: 4401585670 | E39: BUILDERS WAREHOUSE:GLEN EAGLES | F39: AT SEASONAL COLOUR 12CM POT 850040171 | G39: -8 | H39: 7 | I39: -56 | J39: -448 | K39: {=_xlfn.LET(_xlpm.d,UPPER(TRIM(CLEAN(SUBSTITUTE(F39,CHAR(160)," ")))),_xlpm.keys,UPPER(TRIM(MAP!$B$1:$B$401)),_xlpm.vals,MAP!$A$1:$A$401,_xlpm.matchlen,IF(ISNUMBER(SEARCH(_xlpm.keys,_xlpm.d)),LEN(_xlpm.keys),0),_xlpm.best,MAX(_xlpm.matchlen),IF(_xlpm.best=0,"",INDEX(_xlpm.vals,MATCH(_xlpm.best,_xlpm.matchlen,0))))} -> 12CM COLOUR POT
B40: 45996 | C40: Credit Note | D40: 89534A | E40: BUILDERS WAREHOUSE:CARNIVAL MALL | F40: AT SEASONAL COLOUR 12CM POT | G40: -25 | H40: 7 | I40: -175 | J40: -623 | K40: {=_xlfn.LET(_xlpm.d,UPPER(TRIM(CLEAN(SUBSTITUTE(F40,CHAR(160)," ")))),_xlpm.keys,UPPER(TRIM(MAP!$B$1:$B$401)),_xlpm.vals,MAP!$A$1:$A$401,_xlpm.matchlen,IF(ISNUMBER(SEARCH(_xlpm.keys,_xlpm.d)),LEN(_xlpm.keys),0),_xlpm.best,MAX(_xlpm.matchlen),IF(_xlpm.best=0,"",INDEX(_xlpm.vals,MATCH(_xlpm.best,_xlpm.matchlen,0))))} -> 12CM COLOUR POT
B41: 45996 | C41: Credit Note | D41: 89531A | E41: BUILDERS WAREHOUSE:BOKSBURG (NEW) | F41: AT SEASONAL COLOUR 12CM POT 850040171 | G41: -1 | H41: 7 | I41: -7 | J41: -630 | K41: {=_xlfn.LET(_xlpm.d,UPPER(TRIM(CLEAN(SUBSTITUTE(F41,CHAR(160)," ")))),_xlpm.keys,UPPER(TRIM(MAP!$B$1:$B$401)),_xlpm.vals,MAP!$A$1:$A$401,_xlpm.matchlen,IF(ISNUMBER(SEARCH(_xlpm.keys,_xlpm.d)),LEN(_xlpm.keys),0),_xlpm.best,MAX(_xlpm.matchlen),IF(_xlpm.best=0,"",INDEX(_xlpm.vals,MATCH(_xlpm.best,_xlpm.matchlen,0))))} -> 12CM COLOUR POT
B42: 46001 | C42: Credit Note | D42: 4401586981 | E42: BUILDERS WAREHOUSE:CRAIGHALL PARK | F42: AT SEASONAL COLOUR 12CM POT 850040171 | G42: -7 | H42: 7 | I42: -49 | J42: -679 | K42: {=_xlfn.LET(_xlpm.d,UPPER(TRIM(CLEAN(SUBSTITUTE(F42,CHAR(160)," ")))),_xlpm.keys,UPPER(TRIM(MAP!$B$1:$B$401)),_xlpm.vals,MAP!$A$1:$A$401,_xlpm.matchlen,IF(ISNUMBER(SEARCH(_xlpm.keys,_xlpm.d)),LEN(_xlpm.keys),0),_xlpm.best,MAX(_xlpm.matchlen),IF(_xlpm.best=0,"",INDEX(_xlpm.vals,MATCH(_xlpm.best,_xlpm.matchlen,0))))} -> 12CM COLOUR POT
B43: 46008 | C43: Credit Note | D43: 4401588383 | E43: BUILDERS WAREHOUSE:RUSTENBURG | F43: AT SEASONAL COLOUR 12CM POT 850040171 | G43: -6 | H43: 12.2 | I43: -73.2 | J43: -752.2 | K43: {=_xlfn.LET(_xlpm.d,UPPER(TRIM(CLEAN(SUBSTITUTE(F43,CHAR(160)," ")))),_xlpm.keys,UPPER(TRIM(MAP!$B$1:$B$401)),_xlpm.vals,MAP!$A$1:$A$401,_xlpm.matchlen,IF(ISNUMBER(SEARCH(_xlpm.keys,_xlpm.d)),LEN(_xlpm.keys),0),_xlpm.best,MAX(_xlpm.matchlen),IF(_xlpm.best=0,"",INDEX(_xlpm.vals,MATCH(_xlpm.best,_xlpm.matchlen,0))))} -> 12CM COLOUR POT
B44: 46009 | C44: Credit Note | D44: 4401588664 | E44: BUILDERS WAREHOUSE:ROBINDALE | F44: AT SEASONAL COLOUR 12CM POT 850040171 | G44: -18 | H44: 12.2 | I44: -219.6 | J44: -971.8 | K44: {=_xlfn.LET(_xlpm.d,UPPER(TRIM(CLEAN(SUBSTITUTE(F44,CHAR(160)," ")))),_xlpm.keys,UPPER(TRIM(MAP!$B$1:$B$401)),_xlpm.vals,MAP!$A$1:$A$401,_xlpm.matchlen,IF(ISNUMBER(SEARCH(_xlpm.keys,_xlpm.d)),LEN(_xlpm.keys),0),_xlpm.best,MAX(_xlpm.matchlen),IF(_xlpm.best=0,"",INDEX(_xlpm.vals,MATCH(_xlpm.best,_xlpm.matchlen,0))))} -> 12CM COLOUR POT
B45: 46010 | C45: Credit Note | D45: 4401588884 | E45: BUILDERS WAREHOUSE:NEWMARKET | F45: AT SEASONAL COLOUR 12CM POT 850040171 | G45: -55 | H45: 12.2 | I45: -671 | J45: -1642.8 | K45: {=_xlfn.LET(_xlpm.d,UPPER(TRIM(CLEAN(SUBSTITUTE(F45,CHAR(160)," ")))),_xlpm.keys,UPPER(TRIM(MAP!$B$1:$B$401)),_xlpm.vals,MAP!$A$1:$A$401,_xlpm.matchlen,IF(ISNUMBER(SEARCH(_xlpm.keys,_xlpm.d)),LEN(_xlpm.keys),0),_xlpm.best,MAX(_xlpm.matchlen),IF(_xlpm.best=0,"",INDEX(_xlpm.vals,MATCH(_xlpm.best,_xlpm.matchlen,0))))} -> 12CM COLOUR POT
B46: 46013 | C46: Credit Note | D46: 4401589394 | E46: BUILDERS WAREHOUSE:CARNIVAL MALL | F46: AT SEASONAL COLOUR 12CM POT 850040171 | G46: -2 | H46: 12.2 | I46: -24.4 | J46: -1667.2 | K46: {=_xlfn.LET(_xlpm.d,UPPER(TRIM(CLEAN(SUBSTITUTE(F46,CHAR(160)," ")))),_xlpm.keys,UPPER(TRIM(MAP!$B$1:$B$401)),_xlpm.vals,MAP!$A$1:$A$401,_xlpm.matchlen,IF(ISNUMBER(SEARCH(_xlpm.keys,_xlpm.d)),LEN(_xlpm.keys),0),_xlpm.best,MAX(_xlpm.matchlen),IF(_xlpm.best=0,"",INDEX(_xlpm.vals,MATCH(_xlpm.best,_xlpm.matchlen,0))))} -> 12CM COLOUR POT
... B84: 46112 | C84: Credit Note | D84: 4401615870 | E84: BUILDERS WAREHOUSE:BRYANSTON | F84: AT SEASONAL COLOUR 12CM POT 850040171 | G84: -1 | H84: 12.2 | I84: -12.2 | J84: -7627.8 | K84: {=_xlfn.LET(_xlpm.d,UPPER(TRIM(CLEAN(SUBSTITUTE(F84,CHAR(160)," ")))),_xlpm.keys,UPPER(TRIM(MAP!$B$1:$B$401)),_xlpm.vals,MAP!$A$1:$A$401,_xlpm.matchlen,IF(ISNUMBER(SEARCH(_xlpm.keys,_xlpm.d)),LEN(_xlpm.keys),0),_xlpm.best,MAX(_xlpm.matchlen),IF(_xlpm.best=0,"",INDEX(_xlpm.vals,MATCH(_xlpm.best,_xlpm.matchlen,0))))} -> 12CM COLOUR POT
A85: Total for AT SEASONAL COLOUR 12CM POT | G85: -692 | I85: =I35+I36+I37+I38+I39+I40+I41+I42+I43+I44+I45+I46+I47+I48+I49+I50+I51+I52+I53+I54+I55+I56+I57+I58+I59+I60+I61+I62+I63+I64+I65+I66+I67+I68+I69+I70+I71+I72+I73+I74+I75+I76+I77+I78+I79+I80+I81+I82+I83+I84 -> -7627.8 | K85: {=_xlfn.LET(_xlpm.d,UPPER(TRIM(CLEAN(SUBSTITUTE(F85,CHAR(160)," ")))),_xlpm.keys,UPPER(TRIM(MAP!$B$1:$B$401)),_xlpm.vals,MAP!$A$1:$A$401,_xlpm.matchlen,IF(ISNUMBER(SEARCH(_xlpm.keys,_xlpm.d)),LEN(_xlpm.keys),0),_xlpm.best,MAX(_xlpm.matchlen),IF(_xlpm.best=0,"",INDEX(_xlpm.vals,MATCH(_xlpm.best,_xlpm.matchlen,0))))}
A86: AT VEGETABLE POT 12CM | K86: {=_xlfn.LET(_xlpm.d,UPPER(TRIM(CLEAN(SUBSTITUTE(F86,CHAR(160)," ")))),_xlpm.keys,UPPER(TRIM(MAP!$B$1:$B$401)),_xlpm.vals,MAP!$A$1:$A$401,_xlpm.matchlen,IF(ISNUMBER(SEARCH(_xlpm.keys,_xlpm.d)),LEN(_xlpm.keys),0),_xlpm.best,MAX(_xlpm.matchlen),IF(_xlpm.best=0,"",INDEX(_xlpm.vals,MATCH(_xlpm.best,_xlpm.matchlen,0))))}
B87: 46073 | C87: Credit Note | D87: 90245A | E87: BUILDERS WAREHOUSE:LAMBTON | F87: AT VEGETABLE POT 12CM 850040215 | G87: -10 | H87: 12.2 | I87: -122 | J87: -122 | K87: {=_xlfn.LET(_xlpm.d,UPPER(TRIM(CLEAN(SUBSTITUTE(F87,CHAR(160)," ")))),_xlpm.keys,UPPER(TRIM(MAP!$B$1:$B$401)),_xlpm.vals,MAP!$A$1:$A$401,_xlpm.matchlen,IF(ISNUMBER(SEARCH(_xlpm.keys,_xlpm.d)),LEN(_xlpm.keys),0),_xlpm.best,MAX(_xlpm.matchlen),IF(_xlpm.best=0,"",INDEX(_xlpm.vals,MATCH(_xlpm.best,_xlpm.matchlen,0))))} -> 12CM HERB/VEG
B88: 46084 | C88: Credit Note | D88: 4401606695 | E88: BUILDERS WAREHOUSE:RUSTENBURG | F88: AT VEGETABLE POT 12CM 850040215 | G88: -11 | H88: 12.2 | I88: -134.2 | J88: -256.2 | K88: {=_xlfn.LET(_xlpm.d,UPPER(TRIM(CLEAN(SUBSTITUTE(F88,CHAR(160)," ")))),_xlpm.keys,UPPER(TRIM(MAP!$B$1:$B$401)),_xlpm.vals,MAP!$A$1:$A$401,_xlpm.matchlen,IF(ISNUMBER(SEARCH(_xlpm.keys,_xlpm.d)),LEN(_xlpm.keys),0),_xlpm.best,MAX(_xlpm.matchlen),IF(_xlpm.best=0,"",INDEX(_xlpm.vals,MATCH(_xlpm.best,_xlpm.matchlen,0))))} -> 12CM HERB/VEG
B89: 46091 | C89: Credit Note | D89: 4401608665 | E89: BUILDERS WAREHOUSE:RUSTENBURG | F89: AT VEGETABLE POT 12CM 850040215 | G89: -33 | H89: 12.2 | I89: -402.6 | J89: -658.8 | K89: {=_xlfn.LET(_xlpm.d,UPPER(TRIM(CLEAN(SUBSTITUTE(F89,CHAR(160)," ")))),_xlpm.keys,UPPER(TRIM(MAP!$B$1:$B$401)),_xlpm.vals,MAP!$A$1:$A$401,_xlpm.matchlen,IF(ISNUMBER(SEARCH(_xlpm.keys,_xlpm.d)),LEN(_xlpm.keys),0),_xlpm.best,MAX(_xlpm.matchlen),IF(_xlpm.best=0,"",INDEX(_xlpm.vals,MATCH(_xlpm.best,_xlpm.matchlen,0))))} -> 12CM HERB/VEG
B90: 46091 | C90: Credit Note | D90: 4401608648 | E90: BUILDERS WAREHOUSE:LYNNWOOD | F90: AT VEGETABLE POT 12CM 850040215 | G90: -6 | H90: 12.2 | I90: -73.2 | J90: -732 | K90: {=_xlfn.LET(_xlpm.d,UPPER(TRIM(CLEAN(SUBSTITUTE(F90,CHAR(160)," ")))),_xlpm.keys,UPPER(TRIM(MAP!$B$1:$B$401)),_xlpm.vals,MAP!$A$1:$A$401,_xlpm.matchlen,IF(ISNUMBER(SEARCH(_xlpm.keys,_xlpm.d)),LEN(_xlpm.keys),0),_xlpm.best,MAX(_xlpm.matchlen),IF(_xlpm.best=0,"",INDEX(_xlpm.vals,MATCH(_xlpm.best,_xlpm.matchlen,0))))} -> 12CM HERB/VEG
B91: 46093 | C91: Credit Note | D91: 4401609554 | E91: BUILDERS WAREHOUSE:KLERKSDORP | F91: AT VEGETABLE POT 12CM 850040215 | G91: -18 | H91: 12.2 | I91: -219.6 | J91: -951.6 | K91: {=_xlfn.LET(_xlpm.d,UPPER(TRIM(CLEAN(SUBSTITUTE(F91,CHAR(160)," ")))),_xlpm.keys,UPPER(TRIM(MAP!$B$1:$B$401)),_xlpm.vals,MAP!$A$1:$A$401,_xlpm.matchlen,IF(ISNUMBER(SEARCH(_xlpm.keys,_xlpm.d)),LEN(_xlpm.keys),0),_xlpm.best,MAX(_xlpm.matchlen),IF(_xlpm.best=0,"",INDEX(_xlpm.vals,MATCH(_xlpm.best,_xlpm.matchlen,0))))} -> 12CM HERB/VEG
B92: 46093 | C92: Credit Note | D92: 4401609520 | E92: BUILDERS WAREHOUSE:GREENSTONE | F92: AT VEGETABLE POT 12CM 850040215 | G92: -1 | H92: 12.2 | I92: -12.2 | J92: -963.8 | K92: {=_xlfn.LET(_xlpm.d,UPPER(TRIM(CLEAN(SUBSTITUTE(F92,CHAR(160)," ")))),_xlpm.keys,UPPER(TRIM(MAP!$B$1:$B$401)),_xlpm.vals,MAP!$A$1:$A$401,_xlpm.matchlen,IF(ISNUMBER(SEARCH(_xlpm.keys,_xlpm.d)),LEN(_xlpm.keys),0),_xlpm.best,MAX(_xlpm.matchlen),IF(_xlpm.best=0,"",INDEX(_xlpm.vals,MATCH(_xlpm.best,_xlpm.matchlen,0))))} -> 12CM HERB/VEG
B93: 46093 | C93: Credit Note | D93: 4401609549 | E93: BUILDERS WAREHOUSE:GREENSTONE | F93: AT VEGETABLE POT 12CM 850040215 | G93: -18 | H93: 12.2 | I93: -219.6 | J93: -1183.4 | K93: {=_xlfn.LET(_xlpm.d,UPPER(TRIM(CLEAN(SUBSTITUTE(F93,CHAR(160)," ")))),_xlpm.keys,UPPER(TRIM(MAP!$B$1:$B$401)),_xlpm.vals,MAP!$A$1:$A$401,_xlpm.matchlen,IF(ISNUMBER(SEARCH(_xlpm.keys,_xlpm.d)),LEN(_xlpm.keys),0),_xlpm.best,MAX(_xlpm.matchlen),IF(_xlpm.best=0,"",INDEX(_xlpm.vals,MATCH(_xlpm.best,_xlpm.matchlen,0))))} -> 12CM HERB/VEG
B94: 46094 | C94: Credit Note | D94: 4401610091 | E94: BUILDERS WAREHOUSE:NEWMARKET | F94: AT VEGETABLE POT 12CM 850040215 | G94: -19 | H94: 12.2 | I94: -231.8 | J94: -1415.2 | K94: {=_xlfn.LET(_xlpm.d,UPPER(TRIM(CLEAN(SUBSTITUTE(F94,CHAR(160)," ")))),_xlpm.keys,UPPER(TRIM(MAP!$B$1:$B$401)),_xlpm.vals,MAP!$A$1:$A$401,_xlpm.matchlen,IF(ISNUMBER(SEARCH(_xlpm.keys,_xlpm.d)),LEN(_xlpm.keys),0),_xlpm.best,MAX(_xlpm.matchlen),IF(_xlpm.best=0,"",INDEX(_xlpm.vals,MATCH(_xlpm.best,_xlpm.matchlen,0))))} -> 12CM HERB/VEG
B95: 46097 | C95: Credit Note | D95: 4401610724 | E95: BUILDERS WAREHOUSE:BOKSBURG (NEW) | F95: AT VEGETABLE POT 12CM 850040215 | G95: -41 | H95: 12.2 | I95: -500.2 | J95: -1915.4 | K95: {=_xlfn.LET(_xlpm.d,UPPER(TRIM(CLEAN(SUBSTITUTE(F95,CHAR(160)," ")))),_xlpm.keys,UPPER(TRIM(MAP!$B$1:$B$401)),_xlpm.vals,MAP!$A$1:$A$401,_xlpm.matchlen,IF(ISNUMBER(SEARCH(_xlpm.keys,_xlpm.d)),LEN(_xlpm.keys),0),_xlpm.best,MAX(_xlpm.matchlen),IF(_xlpm.best=0,"",INDEX(_xlpm.vals,MATCH(_xlpm.best,_xlpm.matchlen,0))))} -> 12CM HERB/VEG
B96: 46098 | C96: Credit Note | D96: 4401611207 | E96: BUILDERS WAREHOUSE:CENTURION | F96: AT VEGETABLE POT 12CM 850040215 | G96: -20 | H96: 12.2 | I96: -244 | J96: -2159.4 | K96: {=_xlfn.LET(_xlpm.d,UPPER(TRIM(CLEAN(SUBSTITUTE(F96,CHAR(160)," ")))),_xlpm.keys,UPPER(TRIM(MAP!$B$1:$B$401)),_xlpm.vals,MAP!$A$1:$A$401,_xlpm.matchlen,IF(ISNUMBER(SEARCH(_xlpm.keys,_xlpm.d)),LEN(_xlpm.keys),0),_xlpm.best,MAX(_xlpm.matchlen),IF(_xlpm.best=0,"",INDEX(_xlpm.vals,MATCH(_xlpm.best,_xlpm.matchlen,0))))} -> 12CM HERB/VEG
B97: 46098 | C97: Credit Note | D97: 4401611232 | E97: BUILDERS WAREHOUSE:RASLOUW | F97: AT VEGETABLE POT 12CM 850040215 | G97: -11 | H97: 12.2 | I97: -134.2 | J97: -2293.6 | K97: {=_xlfn.LET(_xlpm.d,UPPER(TRIM(CLEAN(SUBSTITUTE(F97,CHAR(160)," ")))),_xlpm.keys,UPPER(TRIM(MAP!$B$1:$B$401)),_xlpm.vals,MAP!$A$1:$A$401,_xlpm.matchlen,IF(ISNUMBER(SEARCH(_xlpm.keys,_xlpm.d)),LEN(_xlpm.keys),0),_xlpm.best,MAX(_xlpm.matchlen),IF(_xlpm.best=0,"",INDEX(_xlpm.vals,MATCH(_xlpm.best,_xlpm.matchlen,0))))} -> 12CM HERB/VEG
B98: 46100 | C98: Credit Note | D98: 4401612173 | E98: BUILDERS WAREHOUSE:KLERKSDORP | F98: AT VEGETABLE POT 12CM 850040215 | G98: -5 | H98: 12.2 | I98: -61 | J98: -2354.6 | K98: {=_xlfn.LET(_xlpm.d,UPPER(TRIM(CLEAN(SUBSTITUTE(F98,CHAR(160)," ")))),_xlpm.keys,UPPER(TRIM(MAP!$B$1:$B$401)),_xlpm.vals,MAP!$A$1:$A$401,_xlpm.matchlen,IF(ISNUMBER(SEARCH(_xlpm.keys,_xlpm.d)),LEN(_xlpm.keys),0),_xlpm.best,MAX(_xlpm.matchlen),IF(_xlpm.best=0,"",INDEX(_xlpm.vals,MATCH(_xlpm.best,_xlpm.matchlen,0))))} -> 12CM HERB/VEG
... B103: 46108 | C103: Credit Note | D103: 1335 | E103: THYME SQUARE | F103: AT VEGETABLE POT 12CM | G103: -1 | H103: 22.9 | I103: -22.9 | J103: -3268.1 | K103: {=_xlfn.LET(_xlpm.d,UPPER(TRIM(CLEAN(SUBSTITUTE(F103,CHAR(160)," ")))),_xlpm.keys,UPPER(TRIM(MAP!$B$1:$B$401)),_xlpm.vals,MAP!$A$1:$A$401,_xlpm.matchlen,IF(ISNUMBER(SEARCH(_xlpm.keys,_xlpm.d)),LEN(_xlpm.keys),0),_xlpm.best,MAX(_xlpm.matchlen),IF(_xlpm.best=0,"",INDEX(_xlpm.vals,MATCH(_xlpm.best,_xlpm.matchlen,0))))} -> 12CM HERB/VEG
A104: Total for AT VEGETABLE POT 12CM | G104: -267 | I104: =I87+I88+I89+I90+I91+I92+I93+I94+I95+I96+I97+I98+I99+I100+I101+I102+I103 -> -3268.1 | K104: {=_xlfn.LET(_xlpm.d,UPPER(TRIM(CLEAN(SUBSTITUTE(F104,CHAR(160)," ")))),_xlpm.keys,UPPER(TRIM(MAP!$B$1:$B$401)),_xlpm.vals,MAP!$A$1:$A$401,_xlpm.matchlen,IF(ISNUMBER(SEARCH(_xlpm.keys,_xlpm.d)),LEN(_xlpm.keys),0),_xlpm.best,MAX(_xlpm.matchlen),IF(_xlpm.best=0,"",INDEX(_xlpm.vals,MATCH(_xlpm.best,_xlpm.matchlen,0))))}
A105: AT CELOSIA 12CM POT | K105: {=_xlfn.LET(_xlpm.d,UPPER(TRIM(CLEAN(SUBSTITUTE(F105,CHAR(160)," ")))),_xlpm.keys,UPPER(TRIM(MAP!$B$1:$B$401)),_xlpm.vals,MAP!$A$1:$A$401,_xlpm.matchlen,IF(ISNUMBER(SEARCH(_xlpm.keys,_xlpm.d)),LEN(_xlpm.keys),0),_xlpm.best,MAX(_xlpm.matchlen),IF(_xlpm.best=0,"",INDEX(_xlpm.vals,MATCH(_xlpm.best,_xlpm.matchlen,0))))}
B106: 45660 | C106: Credit Note | D106: 1103 | E106: THYME SQUARE | F106: AT CELOSIA 12CM POT | G106: -5 | H106: 11.25 | I106: -56.25 | J106: -56.25 | K106: {=_xlfn.LET(_xlpm.d,UPPER(TRIM(CLEAN(SUBSTITUTE(F106,CHAR(160)," ")))),_xlpm.keys,UPPER(TRIM(MAP!$B$1:$B$401)),_xlpm.vals,MAP!$A$1:$A$401,_xlpm.matchlen,IF(ISNUMBER(SEARCH(_xlpm.keys,_xlpm.d)),LEN(_xlpm.keys),0),_xlpm.best,MAX(_xlpm.matchlen),IF(_xlpm.best=0,"",INDEX(_xlpm.vals,MATCH(_xlpm.best,_xlpm.matchlen,0))))} -> 12CM COLOUR POT
B107: 45699 | C107: Credit Note | D107: 86467A | E107: BUILDERS WAREHOUSE:WONDER PARK | F107: AT CELOSIA 12CM POT | G107: -20 | H107: 19.65 | I107: -393 | J107: -449.25 | K107: {=_xlfn.LET(_xlpm.d,UPPER(TRIM(CLEAN(SUBSTITUTE(F107,CHAR(160)," ")))),_xlpm.keys,UPPER(TRIM(MAP!$B$1:$B$401)),_xlpm.vals,MAP!$A$1:$A$401,_xlpm.matchlen,IF(ISNUMBER(SEARCH(_xlpm.keys,_xlpm.d)),LEN(_xlpm.keys),0),_xlpm.best,MAX(_xlpm.matchlen),IF(_xlpm.best=0,"",INDEX(_xlpm.vals,MATCH(_xlpm.best,_xlpm.matchlen,0))))} -> 12CM COLOUR POT
B108: 45720 | C108: Credit Note | D108: 86677A | E108: BUILDERS WAREHOUSE:WONDER PARK | F108: AT CELOSIA 12CM POT 754865 | G108: -10 | H108: 12.2 | I108: -122 | J108: -571.25 | K108: {=_xlfn.LET(_xlpm.d,UPPER(TRIM(CLEAN(SUBSTITUTE(F108,CHAR(160)," ")))),_xlpm.keys,UPPER(TRIM(MAP!$B$1:$B$401)),_xlpm.vals,MAP!$A$1:$A$401,_xlpm.matchlen,IF(ISNUMBER(SEARCH(_xlpm.keys,_xlpm.d)),LEN(_xlpm.keys),0),_xlpm.best,MAX(_xlpm.matchlen),IF(_xlpm.best=0,"",INDEX(_xlpm.vals,MATCH(_xlpm.best,_xlpm.matchlen,0))))} -> 12CM COLOUR POT
B109: 45744 | C109: Credit Note | D109: 4401504693 | E109: BUILDERS WAREHOUSE:EDENVALE | F109: AT CELOSIA 12CM POT 754865 | G109: -1 | H109: 12.2 | I109: -12.2 | J109: -583.45 | K109: {=_xlfn.LET(_xlpm.d,UPPER(TRIM(CLEAN(SUBSTITUTE(F109,CHAR(160)," ")))),_xlpm.keys,UPPER(TRIM(MAP!$B$1:$B$401)),_xlpm.vals,MAP!$A$1:$A$401,_xlpm.matchlen,IF(ISNUMBER(SEARCH(_xlpm.keys,_xlpm.d)),LEN(_xlpm.keys),0),_xlpm.best,MAX(_xlpm.matchlen),IF(_xlpm.best=0,"",INDEX(_xlpm.vals,MATCH(_xlpm.best,_xlpm.matchlen,0))))} -> 12CM COLOUR POT
B110: 45762 | C110: Credit Note | D110: 87046A | E110: BUILDERS WAREHOUSE:GEZINA NEW | F110: AT CELOSIA 12CM POT 754865 | G110: -100 | H110: 12.2 | I110: -1220 | J110: -1803.45 | K110: {=_xlfn.LET(_xlpm.d,UPPER(TRIM(CLEAN(SUBSTITUTE(F110,CHAR(160)," ")))),_xlpm.keys,UPPER(TRIM(MAP!$B$1:$B$401)),_xlpm.vals,MAP!$A$1:$A$401,_xlpm.matchlen,IF(ISNUMBER(SEARCH(_xlpm.keys,_xlpm.d)),LEN(_xlpm.keys),0),_xlpm.best,MAX(_xlpm.matchlen),IF(_xlpm.best=0,"",INDEX(_xlpm.vals,MATCH(_xlpm.best,_xlpm.matchlen,0))))} -> 12CM COLOUR POT
B111: 45762 | C111: Credit Note | D111: 4401509877 | E111: BUILDERS WAREHOUSE:WOODLANDS | F111: AT CELOSIA 12CM POT 754865 | G111: -25 | H111: 12.2 | I111: -305 | J111: -2108.45 | K111: {=_xlfn.LET(_xlpm.d,UPPER(TRIM(CLEAN(SUBSTITUTE(F111,CHAR(160)," ")))),_xlpm.keys,UPPER(TRIM(MAP!$B$1:$B$401)),_xlpm.vals,MAP!$A$1:$A$401,_xlpm.matchlen,IF(ISNUMBER(SEARCH(_xlpm.keys,_xlpm.d)),LEN(_xlpm.keys),0),_xlpm.best,MAX(_xlpm.matchlen),IF(_xlpm.best=0,"",INDEX(_xlpm.vals,MATCH(_xlpm.best,_xlpm.matchlen,0))))} -> 12CM COLOUR POT
B112: 45763 | C112: Credit Note | D112: 4401510492 | E112: BUILDERS WAREHOUSE:ZAMBEZI | F112: AT CELOSIA 12CM POT | G112: -16 | H112: 12.2 | I112: -195.2 | J112: -2303.65 | K112: {=_xlfn.LET(_xlpm.d,UPPER(TRIM(CLEAN(SUBSTITUTE(F112,CHAR(160)," ")))),_xlpm.keys,UPPER(TRIM(MAP!$B$1:$B$401)),_xlpm.vals,MAP!$A$1:$A$401,_xlpm.matchlen,IF(ISNUMBER(SEARCH(_xlpm.keys,_xlpm.d)),LEN(_xlpm.keys),0),_xlpm.best,MAX(_xlpm.matchlen),IF(_xlpm.best=0,"",INDEX(_xlpm.vals,MATCH(_xlpm.best,_xlpm.matchlen,0))))} -> 12CM COLOUR POT
B113: 45764 | C113: Credit Note | D113: 4401510885 | E113: BUILDERS WAREHOUSE:NORTHMEAD | F113: AT CELOSIA 12CM POT 754865 | G113: -2 | H113: 12.2 | I113: -24.4 | J113: -2328.05 | K113: {=_xlfn.LET(_xlpm.d,UPPER(TRIM(CLEAN(SUBSTITUTE(F113,CHAR(160)," ")))),_xlpm.keys,UPPER(TRIM(MAP!$B$1:$B$401)),_xlpm.vals,MAP!$A$1:$A$401,_xlpm.matchlen,IF(ISNUMBER(SEARCH(_xlpm.keys,_xlpm.d)),LEN(_xlpm.keys),0),_xlpm.best,MAX(_xlpm.matchlen),IF(_xlpm.best=0,"",INDEX(_xlpm.vals,MATCH(_xlpm.best,_xlpm.matchlen,0))))} -> 12CM COLOUR POT
B114: 45770 | C114: Credit Note | D114: 4401512091 | E114: BUILDERS WAREHOUSE:ZAMBEZI | F114: AT CELOSIA 12CM POT 754865 | G114: -35 | H114: 12.2 | I114: -427 | J114: -2755.05 | K114: {=_xlfn.LET(_xlpm.d,UPPER(TRIM(CLEAN(SUBSTITUTE(F114,CHAR(160)," ")))),_xlpm.keys,UPPER(TRIM(MAP!$B$1:$B$401)),_xlpm.vals,MAP!$A$1:$A$401,_xlpm.matchlen,IF(ISNUMBER(SEARCH(_xlpm.keys,_xlpm.d)),LEN(_xlpm.keys),0),_xlpm.best,MAX(_xlpm.matchlen),IF(_xlpm.best=0,"",INDEX(_xlpm.vals,MATCH(_xlpm.best,_xlpm.matchlen,0))))} -> 12CM COLOUR POT
B115: 45770 | C115: Credit Note | D115: 4401512027 | E115: BUILDERS WAREHOUSE:CHERRY LANE | F115: AT CELOSIA 12CM POT 754865 | G115: -6 | H115: 12.2 | I115: -73.2 | J115: -2828.25 | K115: {=_xlfn.LET(_xlpm.d,UPPER(TRIM(CLEAN(SUBSTITUTE(F115,CHAR(160)," ")))),_xlpm.keys,UPPER(TRIM(MAP!$B$1:$B$401)),_xlpm.vals,MAP!$A$1:$A$401,_xlpm.matchlen,IF(ISNUMBER(SEARCH(_xlpm.keys,_xlpm.d)),LEN(_xlpm.keys),0),_xlpm.best,MAX(_xlpm.matchlen),IF(_xlpm.best=0,"",INDEX(_xlpm.vals,MATCH(_xlpm.best,_xlpm.matchlen,0))))} -> 12CM COLOUR POT
B116: 45777 | C116: Credit Note | D116: 4401513933 | E116: BUILDERS WAREHOUSE:ZAMBEZI | F116: AT CELOSIA 12CM POT 754865 | G116: -10 | H116: 12.2 | I116: -122 | J116: -2950.25 | K116: {=_xlfn.LET(_xlpm.d,UPPER(TRIM(CLEAN(SUBSTITUTE(F116,CHAR(160)," ")))),_xlpm.keys,UPPER(TRIM(MAP!$B$1:$B$401)),_xlpm.vals,MAP!$A$1:$A$401,_xlpm.matchlen,IF(ISNUMBER(SEARCH(_xlpm.keys,_xlpm.d)),LEN(_xlpm.keys),0),_xlpm.best,MAX(_xlpm.matchlen),IF(_xlpm.best=0,"",INDEX(_xlpm.vals,MATCH(_xlpm.best,_xlpm.matchlen,0))))} -> 12CM COLOUR POT
B117: 45783 | C117: Credit Note | D117: 4401515200 | E117: BUILDERS WAREHOUSE:ZAMBEZI | F117: AT CELOSIA 12CM POT 754865 | G117: -10 | H117: 12.2 | I117: -122 | J117: -3072.25 | K117: {=_xlfn.LET(_xlpm.d,UPPER(TRIM(CLEAN(SUBSTITUTE(F117,CHAR(160)," ")))),_xlpm.keys,UPPER(TRIM(MAP!$B$1:$B$401)),_xlpm.vals,MAP!$A$1:$A$401,_xlpm.matchlen,IF(ISNUMBER(SEARCH(_xlpm.keys,_xlpm.d)),LEN(_xlpm.keys),0),_xlpm.best,MAX(_xlpm.matchlen),IF(_xlpm.best=0,"",INDEX(_xlpm.vals,MATCH(_xlpm.best,_xlpm.matchlen,0))))} -> 12CM COLOUR POT
... B235: 46087 | C235: Credit Note | D235: 4401607739 | E235: BUILDERS WAREHOUSE:CARNIVAL MALL | F235: AT CELOSIA 12CM POT 754865 | G235: -1 | H235: 12.8 | I235: -12.8 | J235: -23793.65 | K235: {=_xlfn.LET(_xlpm.d,UPPER(TRIM(CLEAN(SUBSTITUTE(F235,CHAR(160)," ")))),_xlpm.keys,UPPER(TRIM(MAP!$B$1:$B$401)),_xlpm.vals,MAP!$A$1:$A$401,_xlpm.matchlen,IF(ISNUMBER(SEARCH(_xlpm.keys,_xlpm.d)),LEN(_xlpm.keys),0),_xlpm.best,MAX(_xlpm.matchlen),IF(_xlpm.best=0,"",INDEX(_xlpm.vals,MATCH(_xlpm.best,_xlpm.matchlen,0))))} -> 12CM COLOUR POT
A236: Total for AT CELOSIA 12CM POT | G236: -1886 | I236: =I106+I107+I108+I109+I110+I111+I112+I113+I114+I115+I116+I117+I118+I119+I120+I121+I122+I123+I124+I125+I126+I127+I128+I129+I130+I131+I132+I133+I134+I135+I136+I137+I138+I139+I140+I141+I142+I143+I144+I145+I146+I147+I148+I149+I150+I151+I152+I153+I154+I155+I156+I157+I158+I159+I160+I161+I162+I163+I164+I165+I166+I167+I168+I169+I170+I171+I172+I173+I174+I175+I176+I177+I178+I179+I180+I181+I182+I183+I184+I185+I186+I187+I188+I189+I190+I191+I192+I193+I194+I195+I196+I197+I198+I199+I200+I201+I202+I203+I204+I205+I206+I207+I208+I209+I210+I211+I212+I213+I214+I215+I216+I217+I218+I219+I220+I221+I222+I223+I224+I225+I226+I227+I228+I229+I230+I231+I232+I233+I234+I235 -> -23793.65 | K236: {=_xlfn.LET(_xlpm.d,UPPER(TRIM(CLEAN(SUBSTITUTE(F236,CHAR(160)," ")))),_xlpm.keys,UPPER(TRIM(MAP!$B$1:$B$401)),_xlpm.vals,MAP!$A$1:$A$401,_xlpm.matchlen,IF(ISNUMBER(SEARCH(_xlpm.keys,_xlpm.d)),LEN(_xlpm.keys),0),_xlpm.best,MAX(_xlpm.matchlen),IF(_xlpm.best=0,"",INDEX(_xlpm.vals,MATCH(_xlpm.best,_xlpm.matchlen,0))))}
A237: AT VINCA POT 12CM | K237: {=_xlfn.LET(_xlpm.d,UPPER(TRIM(CLEAN(SUBSTITUTE(F237,CHAR(160)," ")))),_xlpm.keys,UPPER(TRIM(MAP!$B$1:$B$401)),_xlpm.vals,MAP!$A$1:$A$401,_xlpm.matchlen,IF(ISNUMBER(SEARCH(_xlpm.keys,_xlpm.d)),LEN(_xlpm.keys),0),_xlpm.best,MAX(_xlpm.matchlen),IF(_xlpm.best=0,"",INDEX(_xlpm.vals,MATCH(_xlpm.best,_xlpm.matchlen,0))))}
B238: 46112 | C238: Credit Note | D238: 1277 | E238: ECKARDS GARDEN PAVILION | F238: AT VINCA POT 12CM (SPECIAL) | G238: -36 | H238: 11.95 | I238: -430.2 | J238: -430.2 | K238: {=_xlfn.LET(_xlpm.d,UPPER(TRIM(CLEAN(SUBSTITUTE(F238,CHAR(160)," ")))),_xlpm.keys,UPPER(TRIM(MAP!$B$1:$B$401)),_xlpm.vals,MAP!$A$1:$A$401,_xlpm.matchlen,IF(ISNUMBER(SEARCH(_xlpm.keys,_xlpm.d)),LEN(_xlpm.keys),0),_xlpm.best,MAX(_xlpm.matchlen),IF(_xlpm.best=0,"",INDEX(_xlpm.vals,MATCH(_xlpm.best,_xlpm.matchlen,0))))} -> 12CM COLOUR POT
A239: Total for AT VINCA POT 12CM | G239: -36 | I239: =I238 -> -430.2 | K239: {=_xlfn.LET(_xlpm.d,UPPER(TRIM(CLEAN(SUBSTITUTE(F239,CHAR(160)," ")))),_xlpm.keys,UPPER(TRIM(MAP!$B$1:$B$401)),_xlpm.vals,MAP!$A$1:$A$401,_xlpm.matchlen,IF(ISNUMBER(SEARCH(_xlpm.keys,_xlpm.d)),LEN(_xlpm.keys),0),_xlpm.best,MAX(_xlpm.matchlen),IF(_xlpm.best=0,"",INDEX(_xlpm.vals,MATCH(_xlpm.best,_xlpm.matchlen,0))))}
A240: COLOUR MAGIC 12CM | K240: {=_xlfn.LET(_xlpm.d,UPPER(TRIM(CLEAN(SUBSTITUTE(F240,CHAR(160)," ")))),_xlpm.keys,UPPER(TRIM(MAP!$B$1:$B$401)),_xlpm.vals,MAP!$A$1:$A$401,_xlpm.matchlen,IF(ISNUMBER(SEARCH(_xlpm.keys,_xlpm.d)),LEN(_xlpm.keys),0),_xlpm.best,MAX(_xlpm.matchlen),IF(_xlpm.best=0,"",INDEX(_xlpm.vals,MATCH(_xlpm.best,_xlpm.matchlen,0))))}
B241: 45681 | C241: Credit Note | D241: 86300A | E241: THYME SQUARE | F241: COLOUR MAGIC 12CM | G241: -4 | H241: 21.8 | I241: -87.2 | J241: -87.2 | K241: {=_xlfn.LET(_xlpm.d,UPPER(TRIM(CLEAN(SUBSTITUTE(F241,CHAR(160)," ")))),_xlpm.keys,UPPER(TRIM(MAP!$B$1:$B$401)),_xlpm.vals,MAP!$A$1:$A$401,_xlpm.matchlen,IF(ISNUMBER(SEARCH(_xlpm.keys,_xlpm.d)),LEN(_xlpm.keys),0),_xlpm.best,MAX(_xlpm.matchlen),IF(_xlpm.best=0,"",INDEX(_xlpm.vals,MATCH(_xlpm.best,_xlpm.matchlen,0))))} -> 12CM COLOUR POT
B242: 45702 | C242: Credit Note | D242: 86526A | E242: THYME SQUARE | F242: COLOUR MAGIC VINCA 12CM | G242: -2 | H242: 11.25 | I242: -22.5 | J242: -109.7 | K242: {=_xlfn.LET(_xlpm.d,UPPER(TRIM(CLEAN(SUBSTITUTE(F242,CHAR(160)," ")))),_xlpm.keys,UPPER(TRIM(MAP!$B$1:$B$401)),_xlpm.vals,MAP!$A$1:$A$401,_xlpm.matchlen,IF(ISNUMBER(SEARCH(_xlpm.keys,_xlpm.d)),LEN(_xlpm.keys),0),_xlpm.best,MAX(_xlpm.matchlen),IF(_xlpm.best=0,"",INDEX(_xlpm.vals,MATCH(_xlpm.best,_xlpm.matchlen,0))))} -> 12CM COLOUR POT
B243: 45731 | C243: Credit Note | D243: 86794A | E243: THYME SQUARE | F243: COLOUR MAGIC 12CM | G243: -9 | H243: 11.25 | I243: -101.25 | J243: -210.95 | K243: {=_xlfn.LET(_xlpm.d,UPPER(TRIM(CLEAN(SUBSTITUTE(F243,CHAR(160)," ")))),_xlpm.keys,UPPER(TRIM(MAP!$B$1:$B$401)),_xlpm.vals,MAP!$A$1:$A$401,_xlpm.matchlen,IF(ISNUMBER(SEARCH(_xlpm.keys,_xlpm.d)),LEN(_xlpm.keys),0),_xlpm.best,MAX(_xlpm.matchlen),IF(_xlpm.best=0,"",INDEX(_xlpm.vals,MATCH(_xlpm.best,_xlpm.matchlen,0))))} -> 12CM COLOUR POT
B244: 45749 | C244: Credit Note | D244: 15706 | E244: GARDENSHOP PARKTOWN | F244: CAPISCUM 12CM | G244: -18 | H244: 12.99 | I244: -233.82 | J244: -444.77 | K244: {=_xlfn.LET(_xlpm.d,UPPER(TRIM(CLEAN(SUBSTITUTE(F244,CHAR(160)," ")))),_xlpm.keys,UPPER(TRIM(MAP!$B$1:$B$401)),_xlpm.vals,MAP!$A$1:$A$401,_xlpm.matchlen,IF(ISNUMBER(SEARCH(_xlpm.keys,_xlpm.d)),LEN(_xlpm.keys),0),_xlpm.best,MAX(_xlpm.matchlen),IF(_xlpm.best=0,"",INDEX(_xlpm.vals,MATCH(_xlpm.best,_xlpm.matchlen,0))))} -> 12CM HERB/VEG
B245: 45764 | C245: Credit Note | D245: 87095A | E245: THYME SQUARE | F245: COLOUR MAGIC 12CM | G245: -8 | H245: 11.25 | I245: -90 | J245: -534.77 | K245: {=_xlfn.LET(_xlpm.d,UPPER(TRIM(CLEAN(SUBSTITUTE(F245,CHAR(160)," ")))),_xlpm.keys,UPPER(TRIM(MAP!$B$1:$B$401)),_xlpm.vals,MAP!$A$1:$A$401,_xlpm.matchlen,IF(ISNUMBER(SEARCH(_xlpm.keys,_xlpm.d)),LEN(_xlpm.keys),0),_xlpm.best,MAX(_xlpm.matchlen),IF(_xlpm.best=0,"",INDEX(_xlpm.vals,MATCH(_xlpm.best,_xlpm.matchlen,0))))} -> 12CM COLOUR POT
B246: 45782 | C246: Credit Note | D246: 1856 | E246: THYME SQUARE | F246: VINCA 12CM | G246: -3 | H246: 11.25 | I246: -33.75 | J246: -568.52 | K246: {=_xlfn.LET(_xlpm.d,UPPER(TRIM(CLEAN(SUBSTITUTE(F246,CHAR(160)," ")))),_xlpm.keys,UPPER(TRIM(MAP!$B$1:$B$401)),_xlpm.vals,MAP!$A$1:$A$401,_xlpm.matchlen,IF(ISNUMBER(SEARCH(_xlpm.keys,_xlpm.d)),LEN(_xlpm.keys),0),_xlpm.best,MAX(_xlpm.matchlen),IF(_xlpm.best=0,"",INDEX(_xlpm.vals,MATCH(_xlpm.best,_xlpm.matchlen,0))))} -> 12CM COLOUR POT
B247: 45814 | C247: Credit Note | D247: 1908 | E247: THYME SQUARE | F247: COLOUR MAGIC 12CM | G247: -1 | H247: 11.25 | I247: -11.25 | J247: -579.77 | K247: {=_xlfn.LET(_xlpm.d,UPPER(TRIM(CLEAN(SUBSTITUTE(F247,CHAR(160)," ")))),_xlpm.keys,UPPER(TRIM(MAP!$B$1:$B$401)),_xlpm.vals,MAP!$A$1:$A$401,_xlpm.matchlen,IF(ISNUMBER(SEARCH(_xlpm.keys,_xlpm.d)),LEN(_xlpm.keys),0),_xlpm.best,MAX(_xlpm.matchlen),IF(_xlpm.best=0,"",INDEX(_xlpm.vals,MATCH(_xlpm.best,_xlpm.matchlen,0))))} -> 12CM COLOUR POT
B248: 45849 | C248: Credit Note | D248: 1881 | E248: PLANT FACTORY | F248: COLOUR MAGIC 12CM | G248: -12 | H248: 12.5 | I248: -150 | J248: -729.77 | K248: {=_xlfn.LET(_xlpm.d,UPPER(TRIM(CLEAN(SUBSTITUTE(F248,CHAR(160)," ")))),_xlpm.keys,UPPER(TRIM(MAP!$B$1:$B$401)),_xlpm.vals,MAP!$A$1:$A$401,_xlpm.matchlen,IF(ISNUMBER(SEARCH(_xlpm.keys,_xlpm.d)),LEN(_xlpm.keys),0),_xlpm.best,MAX(_xlpm.matchlen),IF(_xlpm.best=0,"",INDEX(_xlpm.vals,MATCH(_xlpm.best,_xlpm.matchlen,0))))} -> 12CM COLOUR POT
B249: 45856 | C249: Credit Note | D249: 1923 | E249: THYME SQUARE | F249: BELLIS 12CM | G249: -2 | H249: 11.25 | I249: -22.5 | J249: -752.27 | K249: {=_xlfn.LET(_xlpm.d,UPPER(TRIM(CLEAN(SUBSTITUTE(F249,CHAR(160)," ")))),_xlpm.keys,UPPER(TRIM(MAP!$B$1:$B$401)),_xlpm.vals,MAP!$A$1:$A$401,_xlpm.matchlen,IF(ISNUMBER(SEARCH(_xlpm.keys,_xlpm.d)),LEN(_xlpm.keys),0),_xlpm.best,MAX(_xlpm.matchlen),IF(_xlpm.best=0,"",INDEX(_xlpm.vals,MATCH(_xlpm.best,_xlpm.matchlen,0))))} -> 12CM COLOUR POT
B250: 45863 | C250: Credit Note | D250: 1818 | E250: PLANT FACTORY | F250: COLOUR MAGIC 12CM | G250: -8 | H250: 12.5 | I250: -100 | J250: -852.27 | K250: {=_xlfn.LET(_xlpm.d,UPPER(TRIM(CLEAN(SUBSTITUTE(F250,CHAR(160)," ")))),_xlpm.keys,UPPER(TRIM(MAP!$B$1:$B$401)),_xlpm.vals,MAP!$A$1:$A$401,_xlpm.matchlen,IF(ISNUMBER(SEARCH(_xlpm.keys,_xlpm.d)),LEN(_xlpm.keys),0),_xlpm.best,MAX(_xlpm.matchlen),IF(_xlpm.best=0,"",INDEX(_xlpm.vals,MATCH(_xlpm.best,_xlpm.matchlen,0))))} -> 12CM COLOUR POT
B251: 45897 | C251: Credit Note | D251: 15880 | E251: GARDENSHOP PARKTOWN | F251: COLOUR MAGIC 12CM | G251: -1 | H251: 11.9 | I251: -11.9 | J251: -864.17 | K251: {=_xlfn.LET(_xlpm.d,UPPER(TRIM(CLEAN(SUBSTITUTE(F251,CHAR(160)," ")))),_xlpm.keys,UPPER(TRIM(MAP!$B$1:$B$401)),_xlpm.vals,MAP!$A$1:$A$401,_xlpm.matchlen,IF(ISNUMBER(SEARCH(_xlpm.keys,_xlpm.d)),LEN(_xlpm.keys),0),_xlpm.best,MAX(_xlpm.matchlen),IF(_xlpm.best=0,"",INDEX(_xlpm.vals,MATCH(_xlpm.best,_xlpm.matchlen,0))))} -> 12CM COLOUR POT
B252: 45906 | C252: Credit Note | D252: 1824 | E252: THYME SQUARE | F252: COLOUR MAGIC 12CM | G252: -3 | H252: 11.95 | I252: -35.85 | J252: -900.02 | K252: {=_xlfn.LET(_xlpm.d,UPPER(TRIM(CLEAN(SUBSTITUTE(F252,CHAR(160)," ")))),_xlpm.keys,UPPER(TRIM(MAP!$B$1:$B$401)),_xlpm.vals,MAP!$A$1:$A$401,_xlpm.matchlen,IF(ISNUMBER(SEARCH(_xlpm.keys,_xlpm.d)),LEN(_xlpm.keys),0),_xlpm.best,MAX(_xlpm.matchlen),IF(_xlpm.best=0,"",INDEX(_xlpm.vals,MATCH(_xlpm.best,_xlpm.matchlen,0))))} -> 12CM COLOUR POT
... B267: 46108 | C267: Credit Note | D267: 1335 | E267: THYME SQUARE | F267: COLOUR MAGIC 12CM | G267: -6 | H267: 11.95 | I267: -71.7 | J267: -2245.09 | K267: {=_xlfn.LET(_xlpm.d,UPPER(TRIM(CLEAN(SUBSTITUTE(F267,CHAR(160)," ")))),_xlpm.keys,UPPER(TRIM(MAP!$B$1:$B$401)),_xlpm.vals,MAP!$A$1:$A$401,_xlpm.matchlen,IF(ISNUMBER(SEARCH(_xlpm.keys,_xlpm.d)),LEN(_xlpm.keys),0),_xlpm.best,MAX(_xlpm.matchlen),IF(_xlpm.best=0,"",INDEX(_xlpm.vals,MATCH(_xlpm.best,_xlpm.matchlen,0))))} -> 12CM COLOUR POT
A268: Total for COLOUR MAGIC 12CM | G268: -181 | I268: =I241+I242+I243+I244+I245+I246+I247+I248+I249+I250+I251+I252+I253+I254+I255+I256+I257+I258+I259+I260+I261+I262+I263+I264+I265+I266+I267 -> -2245.09 | K268: {=_xlfn.LET(_xlpm.d,UPPER(TRIM(CLEAN(SUBSTITUTE(F268,CHAR(160)," ")))),_xlpm.keys,UPPER(TRIM(MAP!$B$1:$B$401)),_xlpm.vals,MAP!$A$1:$A$401,_xlpm.matchlen,IF(ISNUMBER(SEARCH(_xlpm.keys,_xlpm.d)),LEN(_xlpm.keys),0),_xlpm.best,MAX(_xlpm.matchlen),IF(_xlpm.best=0,"",INDEX(_xlpm.vals,MATCH(_xlpm.best,_xlpm.matchlen,0))))}
A269: PETUNIA 12CM | K269: {=_xlfn.LET(_xlpm.d,UPPER(TRIM(CLEAN(SUBSTITUTE(F269,CHAR(160)," ")))),_xlpm.keys,UPPER(TRIM(MAP!$B$1:$B$401)),_xlpm.vals,MAP!$A$1:$A$401,_xlpm.matchlen,IF(ISNUMBER(SEARCH(_xlpm.keys,_xlpm.d)),LEN(_xlpm.keys),0),_xlpm.best,MAX(_xlpm.matchlen),IF(_xlpm.best=0,"",INDEX(_xlpm.vals,MATCH(_xlpm.best,_xlpm.matchlen,0))))}
B270: 45667 | C270: Credit Note | D270: 4401480198 | E270: BUILDERS WAREHOUSE:EDENVALE | F270: PETUNIA 12CM 250725 | G270: -9 | H270: 12.2 | I270: -109.8 | J270: -109.8 | K270: {=_xlfn.LET(_xlpm.d,UPPER(TRIM(CLEAN(SUBSTITUTE(F270,CHAR(160)," ")))),_xlpm.keys,UPPER(TRIM(MAP!$B$1:$B$401)),_xlpm.vals,MAP!$A$1:$A$401,_xlpm.matchlen,IF(ISNUMBER(SEARCH(_xlpm.keys,_xlpm.d)),LEN(_xlpm.keys),0),_xlpm.best,MAX(_xlpm.matchlen),IF(_xlpm.best=0,"",INDEX(_xlpm.vals,MATCH(_xlpm.best,_xlpm.matchlen,0))))} -> 12CM COLOUR POT
B271: 45670 | C271: Credit Note | D271: 4401480605 | E271: BUILDERS WAREHOUSE:GREENSTONE | F271: PETUNIA 12CM 250725 | G271: -1 | H271: 12.2 | I271: -12.2 | J271: -122 | K271: {=_xlfn.LET(_xlpm.d,UPPER(TRIM(CLEAN(SUBSTITUTE(F271,CHAR(160)," ")))),_xlpm.keys,UPPER(TRIM(MAP!$B$1:$B$401)),_xlpm.vals,MAP!$A$1:$A$401,_xlpm.matchlen,IF(ISNUMBER(SEARCH(_xlpm.keys,_xlpm.d)),LEN(_xlpm.keys),0),_xlpm.best,MAX(_xlpm.matchlen),IF(_xlpm.best=0,"",INDEX(_xlpm.vals,MATCH(_xlpm.best,_xlpm.matchlen,0))))} -> 12CM COLOUR POT
B272: 45671 | C272: Credit Note | D272: 4401480975 | E272: BUILDERS WAREHOUSE:RASLOUW | F272: PETUNIA 12CM 250725 | G272: -6 | H272: 12.2 | I272: -73.2 | J272: -195.2 | K272: {=_xlfn.LET(_xlpm.d,UPPER(TRIM(CLEAN(SUBSTITUTE(F272,CHAR(160)," ")))),_xlpm.keys,UPPER(TRIM(MAP!$B$1:$B$401)),_xlpm.vals,MAP!$A$1:$A$401,_xlpm.matchlen,IF(ISNUMBER(SEARCH(_xlpm.keys,_xlpm.d)),LEN(_xlpm.keys),0),_xlpm.best,MAX(_xlpm.matchlen),IF(_xlpm.best=0,"",INDEX(_xlpm.vals,MATCH(_xlpm.best,_xlpm.matchlen,0))))} -> 12CM COLOUR POT
B273: 45673 | C273: Credit Note | D273: 4401481550 | E273: BUILDERS WAREHOUSE:KLERKSDORP | F273: PETUNIA 12CM 250725 | G273: -1 | H273: 12.2 | I273: -12.2 | J273: -207.4 | K273: {=_xlfn.LET(_xlpm.d,UPPER(TRIM(CLEAN(SUBSTITUTE(F273,CHAR(160)," ")))),_xlpm.keys,UPPER(TRIM(MAP!$B$1:$B$401)),_xlpm.vals,MAP!$A$1:$A$401,_xlpm.matchlen,IF(ISNUMBER(SEARCH(_xlpm.keys,_xlpm.d)),LEN(_xlpm.keys),0),_xlpm.best,MAX(_xlpm.matchlen),IF(_xlpm.best=0,"",INDEX(_xlpm.vals,MATCH(_xlpm.best,_xlpm.matchlen,0))))} -> 12CM COLOUR POT
B274: 45674 | C274: Credit Note | D274: 4401481832 | E274: BUILDERS WAREHOUSE:EDENVALE | F274: PETUNIA 12CM 250725 | G274: -3 | H274: 12.2 | I274: -36.6 | J274: -244 | K274: {=_xlfn.LET(_xlpm.d,UPPER(TRIM(CLEAN(SUBSTITUTE(F274,CHAR(160)," ")))),_xlpm.keys,UPPER(TRIM(MAP!$B$1:$B$401)),_xlpm.vals,MAP!$A$1:$A$401,_xlpm.matchlen,IF(ISNUMBER(SEARCH(_xlpm.keys,_xlpm.d)),LEN(_xlpm.keys),0),_xlpm.best,MAX(_xlpm.matchlen),IF(_xlpm.best=0,"",INDEX(_xlpm.vals,MATCH(_xlpm.best,_xlpm.matchlen,0))))} -> 12CM COLOUR POT
B275: 45681 | C275: Credit Note | D275: 4401483878 | E275: BUILDERS WAREHOUSE:EDENVALE | F275: PETUNIA 12CM 250725 | G275: -6 | H275: 12.2 | I275: -73.2 | J275: -317.2 | K275: {=_xlfn.LET(_xlpm.d,UPPER(TRIM(CLEAN(SUBSTITUTE(F275,CHAR(160)," ")))),_xlpm.keys,UPPER(TRIM(MAP!$B$1:$B$401)),_xlpm.vals,MAP!$A$1:$A$401,_xlpm.matchlen,IF(ISNUMBER(SEARCH(_xlpm.keys,_xlpm.d)),LEN(_xlpm.keys),0),_xlpm.best,MAX(_xlpm.matchlen),IF(_xlpm.best=0,"",INDEX(_xlpm.vals,MATCH(_xlpm.best,_xlpm.matchlen,0))))} -> 12CM COLOUR POT
B276: 45688 | C276: Credit Note | D276: 0887 | E276: FLORICULTURE WHOLESALE GROWERS | F276: PETUNIA 12CM | G276: -20 | H276: 21.8 | I276: -436 | J276: -753.2 | K276: {=_xlfn.LET(_xlpm.d,UPPER(TRIM(CLEAN(SUBSTITUTE(F276,CHAR(160)," ")))),_xlpm.keys,UPPER(TRIM(MAP!$B$1:$B$401)),_xlpm.vals,MAP!$A$1:$A$401,_xlpm.matchlen,IF(ISNUMBER(SEARCH(_xlpm.keys,_xlpm.d)),LEN(_xlpm.keys),0),_xlpm.best,MAX(_xlpm.matchlen),IF(_xlpm.best=0,"",INDEX(_xlpm.vals,MATCH(_xlpm.best,_xlpm.matchlen,0))))} -> 12CM COLOUR POT
...

Sheet MAP
A1: 12CM COLOUR POT | B1: AT SEASONAL COLOUR 12CM POT | E1: SEEDLINGS
A2: 12CM COLOUR POT | B2: CELOSIA 12CM | E2: 15CM COLOUR POTS
A3: 12CM COLOUR POT | B3: AT HYPOESTES POT 12CM 850040155 | E3: 12CM COLOUR POT
A4: 12CM COLOUR POT | B4: AT IMPATIENS POT 12CM 850040109 | E4: 12CM HERB
A5: 12CM COLOUR POT | B5: COLOUR MAGIC 12CM | E5: PETUNIA HYBRIDS
A6: 12CM COLOUR POT | B6: PETUNIA 12CM | E6: PLANT TO PLATE
A7: 12CM PRIMROSE/OBCONICA | B7: PRIMROSE | E7: SIMPLY BEAUTIFUL
A8: 12CM COLOUR POT | B8: VINCA VICTORY GRAPE | E8: MID RANGE
A9: 12CM COLOUR POT | B9: FLOWER POT 12CM | E9: CALIBRACHOA
A10: 12CM HERB/VEG | B10: BASIL | E10: 20CM AERO BOWL
A11: 12CM HERB/VEG | B11: CHIVES | E11: 14CM SUCCULENTS
A12: 12CM HERB/VEG | B12: CORIANDER | E12: 25CM HANGING BASKET
... A24: 12CM HERB/VEG | B24: HERB L/STYLE | E24: CHILLI POT
A25: 12CM ORNAMENTAL CHILLI | B25: ORNAMENTAL CHILLI
A26: 12CM ORNAMENTAL CHILLI | B26: CHILLI ORNAMENTAL
A27: 12CM PATIO RANGE | B27: CALCEOLARIA | E27: LAWN PLUGS
A28: 12CM PATIO RANGE | B28: CINERARIA | E28: 12CM GRASS POTS
A29: 12CM PATIO RANGE | B29: CYCLAMEN | E29: 17CM GERANIUM
A30: 15CM COLOUR POTS | B30: PELARGONIUM
A31: 15CM COLOUR POTS | B31: ALYSSUM CLEAR CRYSTAL
A32: 15CM COLOUR POTS | B32: ANTIRRHINUM
A33: 15CM COLOUR POTS | B33: DIANTHUS
A34: 15CM COLOUR POTS | B34: CELOSIA DRACULA
A35: 15CM COLOUR POTS | B35: COLOUR MAGIC 15CM
A36: 15CM COLOUR POTS | B36: COLOUR MAGIC ALYSSUM
A37: 15CM COLOUR POTS | B37: COLOUR MAGIC BELLIS
A38: 15CM COLOUR POTS | B38: COLOUR MAGIC CALENDULA
A39: 15CM COLOUR POTS | B39: COLOUR MAGIC DIANTHUS
A40: 15CM COLOUR POTS | B40: COLOUR MAGIC GAZANIA
A41: 15CM COLOUR POTS | B41: COLOUR MAGIC GYPSOPHILLA
... A109: COLOUR PLUGS 48 | B109: COLOUR PLUGS 48
A110: SEEDLINGS | B110: 28884
A111: SEEDLINGS | B111: SEEDLING FLOWER 6 PACK
A112: SEEDLINGS | B112: SEEDLING VEGETABLE 6 PACK
A113: SEEDLINGS | B113: VEGETABLE SEEDLINGS 6 PACK
A114: 9CM SUCCULENTS | B114: COLOUR MAGIC 9CM
A115: 9CM SUCCULENTS | B115: ECHEVERIA SET OLIVER
A116: 9CM SUCCULENTS | B116: SUCCULENT 9CM
A117: ADVERTISING | B117: ADVERTISING
A118: BUILDERS REBATE | B118: BUILDERS REBATE
A119: D&H | B119: D&H
A120: DISCOUNT | B120: DISCOUNT
A121: CALIBRACHOA | B121: FLORA SELECT MINI PETUNIA
A122: 17CM BEGONIA | B122: FLORA SELECT BEGONIA
... A277: PLANT TO PLATE | B277: CAPSICUM HABANERO 17CM

Sheet TABLE
A1: Years (Date) | B1: 2026
A2: Months (Date) | B2: Apr
A3: Date | B3: (All)
A5: Row Labels | B5: Sum of Quantity | C5: Percentage
A6: 12CM COLOUR POT | B6: -526 | C6: 0.030769231
A7: 12CM GRASS POTS | B7: -12 | C7: 0.00070195964
A8: 12CM HERB/VEG | B8: -477 | C8: 0.027902896
A9: 12CM PATIO RANGE | B9: -3 | C9: 0.00017548991
A10: 12CM PETUNIA HYBRIDS | B10: -242 | C10: 0.014156186
A11: 14CM SUCCULENTS | B11: -16 | C11: 0.00093594618
A12: 15CM ANGELONIA | B12: -27 | C12: 0.0015794092
A13: 15CM COLOUR POTS | B13: -2125 | C13: 0.12430535
A14: 20CM AERO BOWL | B14: -98 | C14: 0.0057326704
A15: 24 PACKS | B15: -38 | C15: 0.0022228722
A16: 25CM COLOUR POT | B16: -154 | C16: 0.009008482
A17: 25CM HANGING BASKET | B17: -198 | C17: 0.011582334
... A33: Grand Total | B33: -17095 | C33: 1
