Workbook

Sheet SALES
A1: Column1 | B1: Date | C1: Transaction type | D1: Number | E1: Customer full name | F1: Memo/Description | G1: Quantity | H1: Sales price | I1: Amount | J1: Balance | K1: Line
A2: 128 DICHONDRA LAWN | K2: {=_xlfn.LET(_xlpm.d,UPPER(TRIM(CLEAN(SUBSTITUTE(F2,CHAR(160)," ")))),_xlpm.keys,UPPER(TRIM(MAP!$B$2:$B$1000)),_xlpm.vals,MAP!$A$2:$A$1000,_xlpm.matchlen,IF(ISNUMBER(SEARCH(_xlpm.keys,_xlpm.d)),LEN(_xlpm.keys),0),_xlpm.best,MAX(_xlpm.matchlen),IF(_xlpm.best=0,"",INDEX(_xlpm.vals,MATCH(_xlpm.best,_xlpm.matchlen,0))))}
B3: 45670 | C3: Invoice | D3: 86225 | E3: LITTLE AUSTRIA | F3: 128 DICHONDRA LAWN | G3: 2 | H3: 117.3 | I3: 234.6 | J3: 234.6 | K3: {=_xlfn.LET(_xlpm.d,UPPER(TRIM(CLEAN(SUBSTITUTE(F3,CHAR(160)," ")))),_xlpm.keys,UPPER(TRIM(MAP!$B$2:$B$1000)),_xlpm.vals,MAP!$A$2:$A$1000,_xlpm.matchlen,IF(ISNUMBER(SEARCH(_xlpm.keys,_xlpm.d)),LEN(_xlpm.keys),0),_xlpm.best,MAX(_xlpm.matchlen),IF(_xlpm.best=0,"",INDEX(_xlpm.vals,MATCH(_xlpm.best,_xlpm.matchlen,0))))} -> LAWN PLUGS
B4: 45679 | C4: Invoice | D4: 86273 | E4: LITTLE AUSTRIA | F4: 128 DICHONDRA LAWN | G4: 2 | H4: 117.3 | I4: 234.6 | J4: 469.2 | K4: {=_xlfn.LET(_xlpm.d,UPPER(TRIM(CLEAN(SUBSTITUTE(F4,CHAR(160)," ")))),_xlpm.keys,UPPER(TRIM(MAP!$B$2:$B$1000)),_xlpm.vals,MAP!$A$2:$A$1000,_xlpm.matchlen,IF(ISNUMBER(SEARCH(_xlpm.keys,_xlpm.d)),LEN(_xlpm.keys),0),_xlpm.best,MAX(_xlpm.matchlen),IF(_xlpm.best=0,"",INDEX(_xlpm.vals,MATCH(_xlpm.best,_xlpm.matchlen,0))))} -> LAWN PLUGS
B5: 45685 | C5: Invoice | D5: 86329 | E5: CENTRAL NURSERY DEPOT | F5: 128 DICHONDRA LAWN | G5: 25 | H5: 117.3 | I5: 2932.5 | J5: 3401.7 | K5: {=_xlfn.LET(_xlpm.d,UPPER(TRIM(CLEAN(SUBSTITUTE(F5,CHAR(160)," ")))),_xlpm.keys,UPPER(TRIM(MAP!$B$2:$B$1000)),_xlpm.vals,MAP!$A$2:$A$1000,_xlpm.matchlen,IF(ISNUMBER(SEARCH(_xlpm.keys,_xlpm.d)),LEN(_xlpm.keys),0),_xlpm.best,MAX(_xlpm.matchlen),IF(_xlpm.best=0,"",INDEX(_xlpm.vals,MATCH(_xlpm.best,_xlpm.matchlen,0))))} -> LAWN PLUGS
B6: 45688 | C6: Invoice | D6: 86376 | E6: CENTRAL NURSERY DEPOT | F6: 128 DICHONDRA LAWN | G6: 25 | H6: 117.3 | I6: 2932.5 | J6: 6334.2 | K6: {=_xlfn.LET(_xlpm.d,UPPER(TRIM(CLEAN(SUBSTITUTE(F6,CHAR(160)," ")))),_xlpm.keys,UPPER(TRIM(MAP!$B$2:$B$1000)),_xlpm.vals,MAP!$A$2:$A$1000,_xlpm.matchlen,IF(ISNUMBER(SEARCH(_xlpm.keys,_xlpm.d)),LEN(_xlpm.keys),0),_xlpm.best,MAX(_xlpm.matchlen),IF(_xlpm.best=0,"",INDEX(_xlpm.vals,MATCH(_xlpm.best,_xlpm.matchlen,0))))} -> LAWN PLUGS
B7: 45695 | C7: Invoice | D7: 86451 | E7: NINFA GARDEN CENTRE | F7: 128 DICHONDRA LAWN | G7: 5 | H7: 118.8 | I7: 594 | J7: 6928.2 | K7: {=_xlfn.LET(_xlpm.d,UPPER(TRIM(CLEAN(SUBSTITUTE(F7,CHAR(160)," ")))),_xlpm.keys,UPPER(TRIM(MAP!$B$2:$B$1000)),_xlpm.vals,MAP!$A$2:$A$1000,_xlpm.matchlen,IF(ISNUMBER(SEARCH(_xlpm.keys,_xlpm.d)),LEN(_xlpm.keys),0),_xlpm.best,MAX(_xlpm.matchlen),IF(_xlpm.best=0,"",INDEX(_xlpm.vals,MATCH(_xlpm.best,_xlpm.matchlen,0))))} -> LAWN PLUGS
B8: 45763 | C8: Invoice | D8: 87097 | E8: LITTLE AUSTRIA | F8: 128 DICHONDRA LAWN | G8: 4 | H8: 117.3 | I8: 469.2 | J8: 7397.4 | K8: {=_xlfn.LET(_xlpm.d,UPPER(TRIM(CLEAN(SUBSTITUTE(F8,CHAR(160)," ")))),_xlpm.keys,UPPER(TRIM(MAP!$B$2:$B$1000)),_xlpm.vals,MAP!$A$2:$A$1000,_xlpm.matchlen,IF(ISNUMBER(SEARCH(_xlpm.keys,_xlpm.d)),LEN(_xlpm.keys),0),_xlpm.best,MAX(_xlpm.matchlen),IF(_xlpm.best=0,"",INDEX(_xlpm.vals,MATCH(_xlpm.best,_xlpm.matchlen,0))))} -> LAWN PLUGS
B9: 45800 | C9: Invoice | D9: 87400 | E9: FOUR SEASONS | F9: 128 DICHONDRA LAWN | G9: 3 | H9: 117.3 | I9: 351.9 | J9: 7749.3 | K9: {=_xlfn.LET(_xlpm.d,UPPER(TRIM(CLEAN(SUBSTITUTE(F9,CHAR(160)," ")))),_xlpm.keys,UPPER(TRIM(MAP!$B$2:$B$1000)),_xlpm.vals,MAP!$A$2:$A$1000,_xlpm.matchlen,IF(ISNUMBER(SEARCH(_xlpm.keys,_xlpm.d)),LEN(_xlpm.keys),0),_xlpm.best,MAX(_xlpm.matchlen),IF(_xlpm.best=0,"",INDEX(_xlpm.vals,MATCH(_xlpm.best,_xlpm.matchlen,0))))} -> LAWN PLUGS
B10: 46042 | C10: Invoice | D10: 89923 | E10: JOY GARDENS | F10: 128 DICHONDRA LAWN | G10: 5 | H10: 124.3 | I10: 621.5 | J10: 8370.8 | K10: {=_xlfn.LET(_xlpm.d,UPPER(TRIM(CLEAN(SUBSTITUTE(F10,CHAR(160)," ")))),_xlpm.keys,UPPER(TRIM(MAP!$B$2:$B$1000)),_xlpm.vals,MAP!$A$2:$A$1000,_xlpm.matchlen,IF(ISNUMBER(SEARCH(_xlpm.keys,_xlpm.d)),LEN(_xlpm.keys),0),_xlpm.best,MAX(_xlpm.matchlen),IF(_xlpm.best=0,"",INDEX(_xlpm.vals,MATCH(_xlpm.best,_xlpm.matchlen,0))))} -> LAWN PLUGS
B11: 46044 | C11: Invoice | D11: 89959 | E11: GARDENSHOP PARKTOWN | F11: 128 DICHONDRA LAWN | G11: 5 | H11: 124.3 | I11: 621.5 | J11: 8992.3 | K11: {=_xlfn.LET(_xlpm.d,UPPER(TRIM(CLEAN(SUBSTITUTE(F11,CHAR(160)," ")))),_xlpm.keys,UPPER(TRIM(MAP!$B$2:$B$1000)),_xlpm.vals,MAP!$A$2:$A$1000,_xlpm.matchlen,IF(ISNUMBER(SEARCH(_xlpm.keys,_xlpm.d)),LEN(_xlpm.keys),0),_xlpm.best,MAX(_xlpm.matchlen),IF(_xlpm.best=0,"",INDEX(_xlpm.vals,MATCH(_xlpm.best,_xlpm.matchlen,0))))} -> LAWN PLUGS
B12: 46051 | C12: Invoice | D12: 90028 | E12: CENTRAL NURSERY DEPOT | F12: 128 DICHONDRA LAWN | G12: 39 | H12: 124.3 | I12: 4847.7 | J12: 13840 | K12: {=_xlfn.LET(_xlpm.d,UPPER(TRIM(CLEAN(SUBSTITUTE(F12,CHAR(160)," ")))),_xlpm.keys,UPPER(TRIM(MAP!$B$2:$B$1000)),_xlpm.vals,MAP!$A$2:$A$1000,_xlpm.matchlen,IF(ISNUMBER(SEARCH(_xlpm.keys,_xlpm.d)),LEN(_xlpm.keys),0),_xlpm.best,MAX(_xlpm.matchlen),IF(_xlpm.best=0,"",INDEX(_xlpm.vals,MATCH(_xlpm.best,_xlpm.matchlen,0))))} -> LAWN PLUGS
B13: 46052 | C13: Invoice | D13: 90040 | E13: CENTRAL NURSERY DEPOT | F13: 128 DICHONDRA LAWN | G13: 5 | H13: 124.3 | I13: 621.5 | J13: 14461.5 | K13: {=_xlfn.LET(_xlpm.d,UPPER(TRIM(CLEAN(SUBSTITUTE(F13,CHAR(160)," ")))),_xlpm.keys,UPPER(TRIM(MAP!$B$2:$B$1000)),_xlpm.vals,MAP!$A$2:$A$1000,_xlpm.matchlen,IF(ISNUMBER(SEARCH(_xlpm.keys,_xlpm.d)),LEN(_xlpm.keys),0),_xlpm.best,MAX(_xlpm.matchlen),IF(_xlpm.best=0,"",INDEX(_xlpm.vals,MATCH(_xlpm.best,_xlpm.matchlen,0))))} -> LAWN PLUGS
B14: 46104 | C14: Invoice | D14: 90511 | E14: PRINCESS GROOT BOME | F14: 128 DICHONDRA LAWN | G14: 6 | H14: 124.3 | I14: 745.8 | J14: 15207.3 | K14: {=_xlfn.LET(_xlpm.d,UPPER(TRIM(CLEAN(SUBSTITUTE(F14,CHAR(160)," ")))),_xlpm.keys,UPPER(TRIM(MAP!$B$2:$B$1000)),_xlpm.vals,MAP!$A$2:$A$1000,_xlpm.matchlen,IF(ISNUMBER(SEARCH(_xlpm.keys,_xlpm.d)),LEN(_xlpm.keys),0),_xlpm.best,MAX(_xlpm.matchlen),IF(_xlpm.best=0,"",INDEX(_xlpm.vals,MATCH(_xlpm.best,_xlpm.matchlen,0))))} -> LAWN PLUGS
A15: Total for 128 DICHONDRA LAWN | G15: 126 | I15: =I3+I4+I5+I6+I7+I8+I9+I10+I11+I12+I13+I14 -> 15207.3 | K15: {=_xlfn.LET(_xlpm.d,UPPER(TRIM(CLEAN(SUBSTITUTE(F15,CHAR(160)," ")))),_xlpm.keys,UPPER(TRIM(MAP!$B$2:$B$1000)),_xlpm.vals,MAP!$A$2:$A$1000,_xlpm.matchlen,IF(ISNUMBER(SEARCH(_xlpm.keys,_xlpm.d)),LEN(_xlpm.keys),0),_xlpm.best,MAX(_xlpm.matchlen),IF(_xlpm.best=0,"",INDEX(_xlpm.vals,MATCH(_xlpm.best,_xlpm.matchlen,0))))}
A16: 128 LM LAWN | K16: {=_xlfn.LET(_xlpm.d,UPPER(TRIM(CLEAN(SUBSTITUTE(F16,CHAR(160)," ")))),_xlpm.keys,UPPER(TRIM(MAP!$B$2:$B$1000)),_xlpm.vals,MAP!$A$2:$A$1000,_xlpm.matchlen,IF(ISNUMBER(SEARCH(_xlpm.keys,_xlpm.d)),LEN(_xlpm.keys),0),_xlpm.best,MAX(_xlpm.matchlen),IF(_xlpm.best=0,"",INDEX(_xlpm.vals,MATCH(_xlpm.best,_xlpm.matchlen,0))))}
B17: 45671 | C17: Invoice | D17: 86176 | E17: NINFA GARDEN CENTRE | F17: 128 LM LAWN | G17: 4 | H17: 117.3 | I17: 469.2 | J17: 469.2 | K17: {=_xlfn.LET(_xlpm.d,UPPER(TRIM(CLEAN(SUBSTITUTE(F17,CHAR(160)," ")))),_xlpm.keys,UPPER(TRIM(MAP!$B$2:$B$1000)),_xlpm.vals,MAP!$A$2:$A$1000,_xlpm.matchlen,IF(ISNUMBER(SEARCH(_xlpm.keys,_xlpm.d)),LEN(_xlpm.keys),0),_xlpm.best,MAX(_xlpm.matchlen),IF(_xlpm.best=0,"",INDEX(_xlpm.vals,MATCH(_xlpm.best,_xlpm.matchlen,0))))} -> LAWN PLUGS
B18: 45674 | C18: Invoice | D18: 86223 | E18: HABITITNAK/KEENGRO | F18: 128 LM LAWN | G18: 5 | H18: 117.3 | I18: 586.5 | J18: 1055.7 | K18: {=_xlfn.LET(_xlpm.d,UPPER(TRIM(CLEAN(SUBSTITUTE(F18,CHAR(160)," ")))),_xlpm.keys,UPPER(TRIM(MAP!$B$2:$B$1000)),_xlpm.vals,MAP!$A$2:$A$1000,_xlpm.matchlen,IF(ISNUMBER(SEARCH(_xlpm.keys,_xlpm.d)),LEN(_xlpm.keys),0),_xlpm.best,MAX(_xlpm.matchlen),IF(_xlpm.best=0,"",INDEX(_xlpm.vals,MATCH(_xlpm.best,_xlpm.matchlen,0))))} -> LAWN PLUGS
B19: 45680 | C19: Invoice | D19: 86333 | E19: NYLIES KWEKERY | F19: 128 LM LAWN | G19: 10 | H19: 117.3 | I19: 1173 | J19: 2228.7 | K19: {=_xlfn.LET(_xlpm.d,UPPER(TRIM(CLEAN(SUBSTITUTE(F19,CHAR(160)," ")))),_xlpm.keys,UPPER(TRIM(MAP!$B$2:$B$1000)),_xlpm.vals,MAP!$A$2:$A$1000,_xlpm.matchlen,IF(ISNUMBER(SEARCH(_xlpm.keys,_xlpm.d)),LEN(_xlpm.keys),0),_xlpm.best,MAX(_xlpm.matchlen),IF(_xlpm.best=0,"",INDEX(_xlpm.vals,MATCH(_xlpm.best,_xlpm.matchlen,0))))} -> LAWN PLUGS
B20: 45681 | C20: Invoice | D20: 86303 | E20: GARDENSHOP PARKTOWN | F20: 128 LM LAWN | G20: 10 | H20: 117.3 | I20: 1173 | J20: 3401.7 | K20: {=_xlfn.LET(_xlpm.d,UPPER(TRIM(CLEAN(SUBSTITUTE(F20,CHAR(160)," ")))),_xlpm.keys,UPPER(TRIM(MAP!$B$2:$B$1000)),_xlpm.vals,MAP!$A$2:$A$1000,_xlpm.matchlen,IF(ISNUMBER(SEARCH(_xlpm.keys,_xlpm.d)),LEN(_xlpm.keys),0),_xlpm.best,MAX(_xlpm.matchlen),IF(_xlpm.best=0,"",INDEX(_xlpm.vals,MATCH(_xlpm.best,_xlpm.matchlen,0))))} -> LAWN PLUGS
B21: 45686 | C21: Invoice | D21: 86352 | E21: JOY GARDENS | F21: 128 LM LAWN | G21: 5 | H21: 117.3 | I21: 586.5 | J21: 3988.2 | K21: {=_xlfn.LET(_xlpm.d,UPPER(TRIM(CLEAN(SUBSTITUTE(F21,CHAR(160)," ")))),_xlpm.keys,UPPER(TRIM(MAP!$B$2:$B$1000)),_xlpm.vals,MAP!$A$2:$A$1000,_xlpm.matchlen,IF(ISNUMBER(SEARCH(_xlpm.keys,_xlpm.d)),LEN(_xlpm.keys),0),_xlpm.best,MAX(_xlpm.matchlen),IF(_xlpm.best=0,"",INDEX(_xlpm.vals,MATCH(_xlpm.best,_xlpm.matchlen,0))))} -> LAWN PLUGS
B22: 45688 | C22: Invoice | D22: 86378 | E22: THREE LEAVES NURSERY | F22: 128 LM LAWN | G22: 3 | H22: 117.3 | I22: 351.9 | J22: 4340.1 | K22: {=_xlfn.LET(_xlpm.d,UPPER(TRIM(CLEAN(SUBSTITUTE(F22,CHAR(160)," ")))),_xlpm.keys,UPPER(TRIM(MAP!$B$2:$B$1000)),_xlpm.vals,MAP!$A$2:$A$1000,_xlpm.matchlen,IF(ISNUMBER(SEARCH(_xlpm.keys,_xlpm.d)),LEN(_xlpm.keys),0),_xlpm.best,MAX(_xlpm.matchlen),IF(_xlpm.best=0,"",INDEX(_xlpm.vals,MATCH(_xlpm.best,_xlpm.matchlen,0))))} -> LAWN PLUGS
B23: 45692 | C23: Invoice | D23: 86397 | E23: GARDENSHOP PARKTOWN | F23: 128 LM LAWN | G23: 8 | H23: 117.3 | I23: 938.4 | J23: 5278.5 | K23: {=_xlfn.LET(_xlpm.d,UPPER(TRIM(CLEAN(SUBSTITUTE(F23,CHAR(160)," ")))),_xlpm.keys,UPPER(TRIM(MAP!$B$2:$B$1000)),_xlpm.vals,MAP!$A$2:$A$1000,_xlpm.matchlen,IF(ISNUMBER(SEARCH(_xlpm.keys,_xlpm.d)),LEN(_xlpm.keys),0),_xlpm.best,MAX(_xlpm.matchlen),IF(_xlpm.best=0,"",INDEX(_xlpm.vals,MATCH(_xlpm.best,_xlpm.matchlen,0))))} -> LAWN PLUGS
B24: 45695 | C24: Invoice | D24: 86438 | E24: JOY GARDENS | F24: 128 LM LAWN | G24: 5 | H24: 117.3 | I24: 586.5 | J24: 5865 | K24: {=_xlfn.LET(_xlpm.d,UPPER(TRIM(CLEAN(SUBSTITUTE(F24,CHAR(160)," ")))),_xlpm.keys,UPPER(TRIM(MAP!$B$2:$B$1000)),_xlpm.vals,MAP!$A$2:$A$1000,_xlpm.matchlen,IF(ISNUMBER(SEARCH(_xlpm.keys,_xlpm.d)),LEN(_xlpm.keys),0),_xlpm.best,MAX(_xlpm.matchlen),IF(_xlpm.best=0,"",INDEX(_xlpm.vals,MATCH(_xlpm.best,_xlpm.matchlen,0))))} -> LAWN PLUGS
B25: 45695 | C25: Invoice | D25: 86451 | E25: NINFA GARDEN CENTRE | F25: 128 LM LAWN | G25: 15 | H25: 118.8 | I25: 1782 | J25: 7647 | K25: {=_xlfn.LET(_xlpm.d,UPPER(TRIM(CLEAN(SUBSTITUTE(F25,CHAR(160)," ")))),_xlpm.keys,UPPER(TRIM(MAP!$B$2:$B$1000)),_xlpm.vals,MAP!$A$2:$A$1000,_xlpm.matchlen,IF(ISNUMBER(SEARCH(_xlpm.keys,_xlpm.d)),LEN(_xlpm.keys),0),_xlpm.best,MAX(_xlpm.matchlen),IF(_xlpm.best=0,"",INDEX(_xlpm.vals,MATCH(_xlpm.best,_xlpm.matchlen,0))))} -> LAWN PLUGS
B26: 45700 | C26: Invoice | D26: 86497 | E26: DIE BLOMWINKELTJIE | F26: 128 LM LAWN | G26: 5 | H26: 117.3 | I26: 586.5 | J26: 8233.5 | K26: {=_xlfn.LET(_xlpm.d,UPPER(TRIM(CLEAN(SUBSTITUTE(F26,CHAR(160)," ")))),_xlpm.keys,UPPER(TRIM(MAP!$B$2:$B$1000)),_xlpm.vals,MAP!$A$2:$A$1000,_xlpm.matchlen,IF(ISNUMBER(SEARCH(_xlpm.keys,_xlpm.d)),LEN(_xlpm.keys),0),_xlpm.best,MAX(_xlpm.matchlen),IF(_xlpm.best=0,"",INDEX(_xlpm.vals,MATCH(_xlpm.best,_xlpm.matchlen,0))))} -> LAWN PLUGS
B27: 45709 | C27: Invoice | D27: 86587 | E27: JOY GARDENS | F27: 128 LM LAWN | G27: 13 | H27: 117.3 | I27: 1524.9 | J27: 9758.4 | K27: {=_xlfn.LET(_xlpm.d,UPPER(TRIM(CLEAN(SUBSTITUTE(F27,CHAR(160)," ")))),_xlpm.keys,UPPER(TRIM(MAP!$B$2:$B$1000)),_xlpm.vals,MAP!$A$2:$A$1000,_xlpm.matchlen,IF(ISNUMBER(SEARCH(_xlpm.keys,_xlpm.d)),LEN(_xlpm.keys),0),_xlpm.best,MAX(_xlpm.matchlen),IF(_xlpm.best=0,"",INDEX(_xlpm.vals,MATCH(_xlpm.best,_xlpm.matchlen,0))))} -> LAWN PLUGS
B28: 45709 | C28: Invoice | D28: 86589 | E28: OLIVE GARDENS | F28: 128 LM LAWN | G28: 7 | H28: 117.3 | I28: 821.1 | J28: 10579.5 | K28: {=_xlfn.LET(_xlpm.d,UPPER(TRIM(CLEAN(SUBSTITUTE(F28,CHAR(160)," ")))),_xlpm.keys,UPPER(TRIM(MAP!$B$2:$B$1000)),_xlpm.vals,MAP!$A$2:$A$1000,_xlpm.matchlen,IF(ISNUMBER(SEARCH(_xlpm.keys,_xlpm.d)),LEN(_xlpm.keys),0),_xlpm.best,MAX(_xlpm.matchlen),IF(_xlpm.best=0,"",INDEX(_xlpm.vals,MATCH(_xlpm.best,_xlpm.matchlen,0))))} -> LAWN PLUGS
... B51: 46073 | C51: Invoice | D51: 90252 | E51: NYLIES KWEKERY | F51: 128 LM LAWN | G51: 10 | H51: 126.35 | I51: 1263.5 | J51: 36318 | K51: {=_xlfn.LET(_xlpm.d,UPPER(TRIM(CLEAN(SUBSTITUTE(F51,CHAR(160)," ")))),_xlpm.keys,UPPER(TRIM(MAP!$B$2:$B$1000)),_xlpm.vals,MAP!$A$2:$A$1000,_xlpm.matchlen,IF(ISNUMBER(SEARCH(_xlpm.keys,_xlpm.d)),LEN(_xlpm.keys),0),_xlpm.best,MAX(_xlpm.matchlen),IF(_xlpm.best=0,"",INDEX(_xlpm.vals,MATCH(_xlpm.best,_xlpm.matchlen,0))))} -> LAWN PLUGS
A52: Total for 128 LM LAWN | G52: 308 | I52: =I17+I18+I19+I20+I21+I22+I23+I24+I25+I26+I27+I28+I29+I30+I31+I32+I33+I34+I35+I36+I37+I38+I39+I40+I41+I42+I43+I44+I45+I46+I47+I48+I49+I50+I51 -> 36318 | K52: {=_xlfn.LET(_xlpm.d,UPPER(TRIM(CLEAN(SUBSTITUTE(F52,CHAR(160)," ")))),_xlpm.keys,UPPER(TRIM(MAP!$B$2:$B$1000)),_xlpm.vals,MAP!$A$2:$A$1000,_xlpm.matchlen,IF(ISNUMBER(SEARCH(_xlpm.keys,_xlpm.d)),LEN(_xlpm.keys),0),_xlpm.best,MAX(_xlpm.matchlen),IF(_xlpm.best=0,"",INDEX(_xlpm.vals,MATCH(_xlpm.best,_xlpm.matchlen,0))))}
A53: 128 WONDER LAWN | K53: {=_xlfn.LET(_xlpm.d,UPPER(TRIM(CLEAN(SUBSTITUTE(F53,CHAR(160)," ")))),_xlpm.keys,UPPER(TRIM(MAP!$B$2:$B$1000)),_xlpm.vals,MAP!$A$2:$A$1000,_xlpm.matchlen,IF(ISNUMBER(SEARCH(_xlpm.keys,_xlpm.d)),LEN(_xlpm.keys),0),_xlpm.best,MAX(_xlpm.matchlen),IF(_xlpm.best=0,"",INDEX(_xlpm.vals,MATCH(_xlpm.best,_xlpm.matchlen,0))))}
B54: 46058 | C54: Invoice | D54: 90084 | E54: CENTRAL NURSERY DEPOT | F54: 128 WONDER LAWN | G54: 30 | H54: 124.3 | I54: 3729 | J54: 3729 | K54: {=_xlfn.LET(_xlpm.d,UPPER(TRIM(CLEAN(SUBSTITUTE(F54,CHAR(160)," ")))),_xlpm.keys,UPPER(TRIM(MAP!$B$2:$B$1000)),_xlpm.vals,MAP!$A$2:$A$1000,_xlpm.matchlen,IF(ISNUMBER(SEARCH(_xlpm.keys,_xlpm.d)),LEN(_xlpm.keys),0),_xlpm.best,MAX(_xlpm.matchlen),IF(_xlpm.best=0,"",INDEX(_xlpm.vals,MATCH(_xlpm.best,_xlpm.matchlen,0))))} -> LAWN PLUGS
B55: 46094 | C55: Invoice | D55: 90444 | E55: CASH SALE | F55: 128 WONDER LAWN | G55: 7 | H55: 124.3 | I55: 870.1 | J55: 4599.1 | K55: {=_xlfn.LET(_xlpm.d,UPPER(TRIM(CLEAN(SUBSTITUTE(F55,CHAR(160)," ")))),_xlpm.keys,UPPER(TRIM(MAP!$B$2:$B$1000)),_xlpm.vals,MAP!$A$2:$A$1000,_xlpm.matchlen,IF(ISNUMBER(SEARCH(_xlpm.keys,_xlpm.d)),LEN(_xlpm.keys),0),_xlpm.best,MAX(_xlpm.matchlen),IF(_xlpm.best=0,"",INDEX(_xlpm.vals,MATCH(_xlpm.best,_xlpm.matchlen,0))))} -> LAWN PLUGS
B56: 46099 | C56: Invoice | D56: 90490 | E56: GARDENSHOP PARKTOWN | F56: 128 WONDER LAWN | G56: 5 | H56: 124.3 | I56: 621.5 | J56: 5220.6 | K56: {=_xlfn.LET(_xlpm.d,UPPER(TRIM(CLEAN(SUBSTITUTE(F56,CHAR(160)," ")))),_xlpm.keys,UPPER(TRIM(MAP!$B$2:$B$1000)),_xlpm.vals,MAP!$A$2:$A$1000,_xlpm.matchlen,IF(ISNUMBER(SEARCH(_xlpm.keys,_xlpm.d)),LEN(_xlpm.keys),0),_xlpm.best,MAX(_xlpm.matchlen),IF(_xlpm.best=0,"",INDEX(_xlpm.vals,MATCH(_xlpm.best,_xlpm.matchlen,0))))} -> LAWN PLUGS
A57: Total for 128 WONDER LAWN | G57: 42 | I57: =I54+I55+I56 -> 5220.6 | K57: {=_xlfn.LET(_xlpm.d,UPPER(TRIM(CLEAN(SUBSTITUTE(F57,CHAR(160)," ")))),_xlpm.keys,UPPER(TRIM(MAP!$B$2:$B$1000)),_xlpm.vals,MAP!$A$2:$A$1000,_xlpm.matchlen,IF(ISNUMBER(SEARCH(_xlpm.keys,_xlpm.d)),LEN(_xlpm.keys),0),_xlpm.best,MAX(_xlpm.matchlen),IF(_xlpm.best=0,"",INDEX(_xlpm.vals,MATCH(_xlpm.best,_xlpm.matchlen,0))))}
A58: AT LAWN PLUG SEEDLINGS 128 | K58: {=_xlfn.LET(_xlpm.d,UPPER(TRIM(CLEAN(SUBSTITUTE(F58,CHAR(160)," ")))),_xlpm.keys,UPPER(TRIM(MAP!$B$2:$B$1000)),_xlpm.vals,MAP!$A$2:$A$1000,_xlpm.matchlen,IF(ISNUMBER(SEARCH(_xlpm.keys,_xlpm.d)),LEN(_xlpm.keys),0),_xlpm.best,MAX(_xlpm.matchlen),IF(_xlpm.best=0,"",INDEX(_xlpm.vals,MATCH(_xlpm.best,_xlpm.matchlen,0))))}
B59: 46000 | C59: Invoice | D59: 89548 | E59: BUILDERS WAREHOUSE:RIVONIA | F59: AT LAWN PLUG SEEDLINGS 128 | G59: 5 | H59: 126.35 | I59: 631.75 | J59: 631.75 | K59: {=_xlfn.LET(_xlpm.d,UPPER(TRIM(CLEAN(SUBSTITUTE(F59,CHAR(160)," ")))),_xlpm.keys,UPPER(TRIM(MAP!$B$2:$B$1000)),_xlpm.vals,MAP!$A$2:$A$1000,_xlpm.matchlen,IF(ISNUMBER(SEARCH(_xlpm.keys,_xlpm.d)),LEN(_xlpm.keys),0),_xlpm.best,MAX(_xlpm.matchlen),IF(_xlpm.best=0,"",INDEX(_xlpm.vals,MATCH(_xlpm.best,_xlpm.matchlen,0))))} -> LAWN PLUGS
B60: 46003 | C60: Invoice | D60: 89621 | E60: CENTRAL NURSERY DEPOT | F60: AT LAWN PLUG SEEDLINGS 128 | G60: 5 | H60: 124.3 | I60: 621.5 | J60: 1253.25 | K60: {=_xlfn.LET(_xlpm.d,UPPER(TRIM(CLEAN(SUBSTITUTE(F60,CHAR(160)," ")))),_xlpm.keys,UPPER(TRIM(MAP!$B$2:$B$1000)),_xlpm.vals,MAP!$A$2:$A$1000,_xlpm.matchlen,IF(ISNUMBER(SEARCH(_xlpm.keys,_xlpm.d)),LEN(_xlpm.keys),0),_xlpm.best,MAX(_xlpm.matchlen),IF(_xlpm.best=0,"",INDEX(_xlpm.vals,MATCH(_xlpm.best,_xlpm.matchlen,0))))} -> LAWN PLUGS
B61: 46045 | C61: Invoice | D61: 89974 | E61: BUILDERS WAREHOUSE:RIVONIA | F61: AT LAWN PLUG SEEDLINGS 128 | G61: 5 | H61: 126.35 | I61: 631.75 | J61: 1885 | K61: {=_xlfn.LET(_xlpm.d,UPPER(TRIM(CLEAN(SUBSTITUTE(F61,CHAR(160)," ")))),_xlpm.keys,UPPER(TRIM(MAP!$B$2:$B$1000)),_xlpm.vals,MAP!$A$2:$A$1000,_xlpm.matchlen,IF(ISNUMBER(SEARCH(_xlpm.keys,_xlpm.d)),LEN(_xlpm.keys),0),_xlpm.best,MAX(_xlpm.matchlen),IF(_xlpm.best=0,"",INDEX(_xlpm.vals,MATCH(_xlpm.best,_xlpm.matchlen,0))))} -> LAWN PLUGS
B62: 46052 | C62: Invoice | D62: 90030 | E62: BUILDERS WAREHOUSE:RIVONIA | F62: AT LAWN PLUG SEEDLINGS 128 | G62: 2 | H62: 126.35 | I62: 252.7 | J62: 2137.7 | K62: {=_xlfn.LET(_xlpm.d,UPPER(TRIM(CLEAN(SUBSTITUTE(F62,CHAR(160)," ")))),_xlpm.keys,UPPER(TRIM(MAP!$B$2:$B$1000)),_xlpm.vals,MAP!$A$2:$A$1000,_xlpm.matchlen,IF(ISNUMBER(SEARCH(_xlpm.keys,_xlpm.d)),LEN(_xlpm.keys),0),_xlpm.best,MAX(_xlpm.matchlen),IF(_xlpm.best=0,"",INDEX(_xlpm.vals,MATCH(_xlpm.best,_xlpm.matchlen,0))))} -> LAWN PLUGS
B63: 46066 | C63: Invoice | D63: 90193 | E63: THYME SQUARE | F63: AT LAWN PLUG SEEDLINGS 128 | G63: 8 | H63: 124.5 | I63: 996 | J63: 3133.7 | K63: {=_xlfn.LET(_xlpm.d,UPPER(TRIM(CLEAN(SUBSTITUTE(F63,CHAR(160)," ")))),_xlpm.keys,UPPER(TRIM(MAP!$B$2:$B$1000)),_xlpm.vals,MAP!$A$2:$A$1000,_xlpm.matchlen,IF(ISNUMBER(SEARCH(_xlpm.keys,_xlpm.d)),LEN(_xlpm.keys),0),_xlpm.best,MAX(_xlpm.matchlen),IF(_xlpm.best=0,"",INDEX(_xlpm.vals,MATCH(_xlpm.best,_xlpm.matchlen,0))))} -> LAWN PLUGS
A64: Total for AT LAWN PLUG SEEDLINGS 128 | G64: 25 | I64: =I59+I60+I61+I62+I63 -> 3133.7 | K64: {=_xlfn.LET(_xlpm.d,UPPER(TRIM(CLEAN(SUBSTITUTE(F64,CHAR(160)," ")))),_xlpm.keys,UPPER(TRIM(MAP!$B$2:$B$1000)),_xlpm.vals,MAP!$A$2:$A$1000,_xlpm.matchlen,IF(ISNUMBER(SEARCH(_xlpm.keys,_xlpm.d)),LEN(_xlpm.keys),0),_xlpm.best,MAX(_xlpm.matchlen),IF(_xlpm.best=0,"",INDEX(_xlpm.vals,MATCH(_xlpm.best,_xlpm.matchlen,0))))}
A65: COLOUR PLUGS 128 | K65: {=_xlfn.LET(_xlpm.d,UPPER(TRIM(CLEAN(SUBSTITUTE(F65,CHAR(160)," ")))),_xlpm.keys,UPPER(TRIM(MAP!$B$2:$B$1000)),_xlpm.vals,MAP!$A$2:$A$1000,_xlpm.matchlen,IF(ISNUMBER(SEARCH(_xlpm.keys,_xlpm.d)),LEN(_xlpm.keys),0),_xlpm.best,MAX(_xlpm.matchlen),IF(_xlpm.best=0,"",INDEX(_xlpm.vals,MATCH(_xlpm.best,_xlpm.matchlen,0))))}
B66: 45666 | C66: Invoice | D66: 86132 | E66: LITTLE AUSTRIA | F66: COLOUR PLUGS 128 | G66: 4 | H66: 117.3 | I66: 469.2 | J66: 469.2 | K66: {=_xlfn.LET(_xlpm.d,UPPER(TRIM(CLEAN(SUBSTITUTE(F66,CHAR(160)," ")))),_xlpm.keys,UPPER(TRIM(MAP!$B$2:$B$1000)),_xlpm.vals,MAP!$A$2:$A$1000,_xlpm.matchlen,IF(ISNUMBER(SEARCH(_xlpm.keys,_xlpm.d)),LEN(_xlpm.keys),0),_xlpm.best,MAX(_xlpm.matchlen),IF(_xlpm.best=0,"",INDEX(_xlpm.vals,MATCH(_xlpm.best,_xlpm.matchlen,0))))} -> 128 COLOUR PLUGS
B67: 45692 | C67: Invoice | D67: 86392 | E67: CENTRAL NURSERY DEPOT | F67: COLOUR PLUGS 128 | G67: 22 | H67: 117.3 | I67: 2580.6 | J67: 3049.8 | K67: {=_xlfn.LET(_xlpm.d,UPPER(TRIM(CLEAN(SUBSTITUTE(F67,CHAR(160)," ")))),_xlpm.keys,UPPER(TRIM(MAP!$B$2:$B$1000)),_xlpm.vals,MAP!$A$2:$A$1000,_xlpm.matchlen,IF(ISNUMBER(SEARCH(_xlpm.keys,_xlpm.d)),LEN(_xlpm.keys),0),_xlpm.best,MAX(_xlpm.matchlen),IF(_xlpm.best=0,"",INDEX(_xlpm.vals,MATCH(_xlpm.best,_xlpm.matchlen,0))))} -> 128 COLOUR PLUGS
B70: 45754 | C70: Invoice | D70: 87010 | E70: AMANDLA FARM | F70: COLOUR PLUGS 128 | G70: 6 | H70: 85 | I70: 510 | J70: 17386.8 | K70: {=_xlfn.LET(_xlpm.d,UPPER(TRIM(CLEAN(SUBSTITUTE(F70,CHAR(160)," ")))),_xlpm.keys,UPPER(TRIM(MAP!$B$2:$B$1000)),_xlpm.vals,MAP!$A$2:$A$1000,_xlpm.matchlen,IF(ISNUMBER(SEARCH(_xlpm.keys,_xlpm.d)),LEN(_xlpm.keys),0),_xlpm.best,MAX(_xlpm.matchlen),IF(_xlpm.best=0,"",INDEX(_xlpm.vals,MATCH(_xlpm.best,_xlpm.matchlen,0))))} -> 128 COLOUR PLUGS
B71: 45779 | C71: Invoice | D71: 87175 | E71: AMANDLA FARM | F71: BROCCOLI 128 | G71: 4 | H71: 85 | I71: 340 | J71: 17726.8 | K71: {=_xlfn.LET(_xlpm.d,UPPER(TRIM(CLEAN(SUBSTITUTE(F71,CHAR(160)," ")))),_xlpm.keys,UPPER(TRIM(MAP!$B$2:$B$1000)),_xlpm.vals,MAP!$A$2:$A$1000,_xlpm.matchlen,IF(ISNUMBER(SEARCH(_xlpm.keys,_xlpm.d)),LEN(_xlpm.keys),0),_xlpm.best,MAX(_xlpm.matchlen),IF(_xlpm.best=0,"",INDEX(_xlpm.vals,MATCH(_xlpm.best,_xlpm.matchlen,0))))} -> 128 COLOUR PLUGS
B72: 45779 | C72: Invoice | D72: 87175 | E72: AMANDLA FARM | F72: CAULIFLOWER 128 | G72: 4 | H72: 85 | I72: 340 | J72: 18066.8 | K72: {=_xlfn.LET(_xlpm.d,UPPER(TRIM(CLEAN(SUBSTITUTE(F72,CHAR(160)," ")))),_xlpm.keys,UPPER(TRIM(MAP!$B$2:$B$1000)),_xlpm.vals,MAP!$A$2:$A$1000,_xlpm.matchlen,IF(ISNUMBER(SEARCH(_xlpm.keys,_xlpm.d)),LEN(_xlpm.keys),0),_xlpm.best,MAX(_xlpm.matchlen),IF(_xlpm.best=0,"",INDEX(_xlpm.vals,MATCH(_xlpm.best,_xlpm.matchlen,0))))} -> 128 COLOUR PLUGS
B73: 45867 | C73: Invoice | D73: 87867 | E73: NOKUKHANYA TRADING | F73: CABBAGE PLUGS 128 | G73: 78.056396 | H73: 102.49 | I73: 8000 | J73: 26066.8 | K73: {=_xlfn.LET(_xlpm.d,UPPER(TRIM(CLEAN(SUBSTITUTE(F73,CHAR(160)," ")))),_xlpm.keys,UPPER(TRIM(MAP!$B$2:$B$1000)),_xlpm.vals,MAP!$A$2:$A$1000,_xlpm.matchlen,IF(ISNUMBER(SEARCH(_xlpm.keys,_xlpm.d)),LEN(_xlpm.keys),0),_xlpm.best,MAX(_xlpm.matchlen),IF(_xlpm.best=0,"",INDEX(_xlpm.vals,MATCH(_xlpm.best,_xlpm.matchlen,0))))} -> 128 COLOUR PLUGS
B88: 45961 | C88: Invoice | D88: 89077 | E88: PLANT FACTORY | F88: COLOUR PLUGS 128 | G88: 5 | H88: 124.3 | I88: 621.5 | J88: 29241.26 | K88: {=_xlfn.LET(_xlpm.d,UPPER(TRIM(CLEAN(SUBSTITUTE(F88,CHAR(160)," ")))),_xlpm.keys,UPPER(TRIM(MAP!$B$2:$B$1000)),_xlpm.vals,MAP!$A$2:$A$1000,_xlpm.matchlen,IF(ISNUMBER(SEARCH(_xlpm.keys,_xlpm.d)),LEN(_xlpm.keys),0),_xlpm.best,MAX(_xlpm.matchlen),IF(_xlpm.best=0,"",INDEX(_xlpm.vals,MATCH(_xlpm.best,_xlpm.matchlen,0))))} -> 128 COLOUR PLUGS
B90: 45971 | C90: Invoice | D90: 89178 | E90: SHARONDALE GARDEN CENTRE | F90: COLOUR PLUGS 128 | G90: 4 | H90: 124.3 | I90: 497.2 | J90: 30427.08 | K90: {=_xlfn.LET(_xlpm.d,UPPER(TRIM(CLEAN(SUBSTITUTE(F90,CHAR(160)," ")))),_xlpm.keys,UPPER(TRIM(MAP!$B$2:$B$1000)),_xlpm.vals,MAP!$A$2:$A$1000,_xlpm.matchlen,IF(ISNUMBER(SEARCH(_xlpm.keys,_xlpm.d)),LEN(_xlpm.keys),0),_xlpm.best,MAX(_xlpm.matchlen),IF(_xlpm.best=0,"",INDEX(_xlpm.vals,MATCH(_xlpm.best,_xlpm.matchlen,0))))} -> 128 COLOUR PLUGS
B91: 45982 | C91: Invoice | D91: 89290 | E91: NYLIES KWEKERY | F91: COLOUR PLUGS 128 | G91: 10 | H91: 123.15 | I91: 1231.5 | J91: 31658.58 | K91: {=_xlfn.LET(_xlpm.d,UPPER(TRIM(CLEAN(SUBSTITUTE(F91,CHAR(160)," ")))),_xlpm.keys,UPPER(TRIM(MAP!$B$2:$B$1000)),_xlpm.vals,MAP!$A$2:$A$1000,_xlpm.matchlen,IF(ISNUMBER(SEARCH(_xlpm.keys,_xlpm.d)),LEN(_xlpm.keys),0),_xlpm.best,MAX(_xlpm.matchlen),IF(_xlpm.best=0,"",INDEX(_xlpm.vals,MATCH(_xlpm.best,_xlpm.matchlen,0))))} -> 128 COLOUR PLUGS
B92: 46009 | C92: Invoice | D92: 89664 | E92: RIVERSIDE MICA | F92: L/M GRASS 128 | G92: 2 | H92: 128.99 | I92: 257.98 | J92: 31916.56 | K92: {=_xlfn.LET(_xlpm.d,UPPER(TRIM(CLEAN(SUBSTITUTE(F92,CHAR(160)," ")))),_xlpm.keys,UPPER(TRIM(MAP!$B$2:$B$1000)),_xlpm.vals,MAP!$A$2:$A$1000,_xlpm.matchlen,IF(ISNUMBER(SEARCH(_xlpm.keys,_xlpm.d)),LEN(_xlpm.keys),0),_xlpm.best,MAX(_xlpm.matchlen),IF(_xlpm.best=0,"",INDEX(_xlpm.vals,MATCH(_xlpm.best,_xlpm.matchlen,0))))} -> 128 COLOUR PLUGS
A98: Total for COLOUR PLUGS 128 | G98: 10082.056 | I98: =I66+I67+I68+I69+I70+I71+I72+I73+I74+I75+I76+I77+I78+I79+I80+I81+I82+I83+I84+I85+I86+I87+I88+I89+I90+I91+I92+I93+I94+I95+I96+I97 -> 14847.98 | K98: {=_xlfn.LET(_xlpm.d,UPPER(TRIM(CLEAN(SUBSTITUTE(F98,CHAR(160)," ")))),_xlpm.keys,UPPER(TRIM(MAP!$B$2:$B$1000)),_xlpm.vals,MAP!$A$2:$A$1000,_xlpm.matchlen,IF(ISNUMBER(SEARCH(_xlpm.keys,_xlpm.d)),LEN(_xlpm.keys),0),_xlpm.best,MAX(_xlpm.matchlen),IF(_xlpm.best=0,"",INDEX(_xlpm.vals,MATCH(_xlpm.best,_xlpm.matchlen,0))))}
A99: AT HYPOESTES POT 12CM | K99: {=_xlfn.LET(_xlpm.d,UPPER(TRIM(CLEAN(SUBSTITUTE(F99,CHAR(160)," ")))),_xlpm.keys,UPPER(TRIM(MAP!$B$2:$B$1000)),_xlpm.vals,MAP!$A$2:$A$1000,_xlpm.matchlen,IF(ISNUMBER(SEARCH(_xlpm.keys,_xlpm.d)),LEN(_xlpm.keys),0),_xlpm.best,MAX(_xlpm.matchlen),IF(_xlpm.best=0,"",INDEX(_xlpm.vals,MATCH(_xlpm.best,_xlpm.matchlen,0))))}
B100: 46073 | C100: Invoice | D100: 90247 | E100: THYME SQUARE | F100: AT HYPOESTES POT 12CM | G100: 10 | H100: 11.95 | I100: 119.5 | J100: 119.5 | K100: {=_xlfn.LET(_xlpm.d,UPPER(TRIM(CLEAN(SUBSTITUTE(F100,CHAR(160)," ")))),_xlpm.keys,UPPER(TRIM(MAP!$B$2:$B$1000)),_xlpm.vals,MAP!$A$2:$A$1000,_xlpm.matchlen,IF(ISNUMBER(SEARCH(_xlpm.keys,_xlpm.d)),LEN(_xlpm.keys),0),_xlpm.best,MAX(_xlpm.matchlen),IF(_xlpm.best=0,"",INDEX(_xlpm.vals,MATCH(_xlpm.best,_xlpm.matchlen,0))))} -> 12CM COLOUR POT
B101: 46080 | C101: Invoice | D101: 90305 | E101: THYME SQUARE | F101: AT HYPOESTES POT 12CM | G101: 10 | H101: 11.95 | I101: 119.5 | J101: 239 | K101: {=_xlfn.LET(_xlpm.d,UPPER(TRIM(CLEAN(SUBSTITUTE(F101,CHAR(160)," ")))),_xlpm.keys,UPPER(TRIM(MAP!$B$2:$B$1000)),_xlpm.vals,MAP!$A$2:$A$1000,_xlpm.matchlen,IF(ISNUMBER(SEARCH(_xlpm.keys,_xlpm.d)),LEN(_xlpm.keys),0),_xlpm.best,MAX(_xlpm.matchlen),IF(_xlpm.best=0,"",INDEX(_xlpm.vals,MATCH(_xlpm.best,_xlpm.matchlen,0))))} -> 12CM COLOUR POT
A102: Total for AT HYPOESTES POT 12CM | G102: 20 | I102: =I100+I101 -> 239 | K102: {=_xlfn.LET(_xlpm.d,UPPER(TRIM(CLEAN(SUBSTITUTE(F102,CHAR(160)," ")))),_xlpm.keys,UPPER(TRIM(MAP!$B$2:$B$1000)),_xlpm.vals,MAP!$A$2:$A$1000,_xlpm.matchlen,IF(ISNUMBER(SEARCH(_xlpm.keys,_xlpm.d)),LEN(_xlpm.keys),0),_xlpm.best,MAX(_xlpm.matchlen),IF(_xlpm.best=0,"",INDEX(_xlpm.vals,MATCH(_xlpm.best,_xlpm.matchlen,0))))}
A103: AT IMPATIENS POT 12CM | K103: {=_xlfn.LET(_xlpm.d,UPPER(TRIM(CLEAN(SUBSTITUTE(F103,CHAR(160)," ")))),_xlpm.keys,UPPER(TRIM(MAP!$B$2:$B$1000)),_xlpm.vals,MAP!$A$2:$A$1000,_xlpm.matchlen,IF(ISNUMBER(SEARCH(_xlpm.keys,_xlpm.d)),LEN(_xlpm.keys),0),_xlpm.best,MAX(_xlpm.matchlen),IF(_xlpm.best=0,"",INDEX(_xlpm.vals,MATCH(_xlpm.best,_xlpm.matchlen,0))))}
B104: 46038 | C104: Invoice | D104: 89905 | E104: THYME SQUARE | F104: AT IMPATIENS POT 12CM | G104: 20 | H104: 12.2 | I104: 244 | J104: 244 | K104: {=_xlfn.LET(_xlpm.d,UPPER(TRIM(CLEAN(SUBSTITUTE(F104,CHAR(160)," ")))),_xlpm.keys,UPPER(TRIM(MAP!$B$2:$B$1000)),_xlpm.vals,MAP!$A$2:$A$1000,_xlpm.matchlen,IF(ISNUMBER(SEARCH(_xlpm.keys,_xlpm.d)),LEN(_xlpm.keys),0),_xlpm.best,MAX(_xlpm.matchlen),IF(_xlpm.best=0,"",INDEX(_xlpm.vals,MATCH(_xlpm.best,_xlpm.matchlen,0))))} -> 12CM COLOUR POT
B105: 46044 | C105: Invoice | D105: 89955 | E105: BUILDERS WAREHOUSE:KEMPTON PARK | F105: AT IMPATIENS POT 12CM | G105: 50 | H105: 12.2 | I105: 610 | J105: 854 | K105: {=_xlfn.LET(_xlpm.d,UPPER(TRIM(CLEAN(SUBSTITUTE(F105,CHAR(160)," ")))),_xlpm.keys,UPPER(TRIM(MAP!$B$2:$B$1000)),_xlpm.vals,MAP!$A$2:$A$1000,_xlpm.matchlen,IF(ISNUMBER(SEARCH(_xlpm.keys,_xlpm.d)),LEN(_xlpm.keys),0),_xlpm.best,MAX(_xlpm.matchlen),IF(_xlpm.best=0,"",INDEX(_xlpm.vals,MATCH(_xlpm.best,_xlpm.matchlen,0))))} -> 12CM COLOUR POT
A106: Total for AT IMPATIENS POT 12CM | G106: 70 | I106: =I104+I105 -> 854 | K106: {=_xlfn.LET(_xlpm.d,UPPER(TRIM(CLEAN(SUBSTITUTE(F106,CHAR(160)," ")))),_xlpm.keys,UPPER(TRIM(MAP!$B$2:$B$1000)),_xlpm.vals,MAP!$A$2:$A$1000,_xlpm.matchlen,IF(ISNUMBER(SEARCH(_xlpm.keys,_xlpm.d)),LEN(_xlpm.keys),0),_xlpm.best,MAX(_xlpm.matchlen),IF(_xlpm.best=0,"",INDEX(_xlpm.vals,MATCH(_xlpm.best,_xlpm.matchlen,0))))}
A107: AT PETUNIA HYBRIDS POT 12CM | K107: {=_xlfn.LET(_xlpm.d,UPPER(TRIM(CLEAN(SUBSTITUTE(F107,CHAR(160)," ")))),_xlpm.keys,UPPER(TRIM(MAP!$B$2:$B$1000)),_xlpm.vals,MAP!$A$2:$A$1000,_xlpm.matchlen,IF(ISNUMBER(SEARCH(_xlpm.keys,_xlpm.d)),LEN(_xlpm.keys),0),_xlpm.best,MAX(_xlpm.matchlen),IF(_xlpm.best=0,"",INDEX(_xlpm.vals,MATCH(_xlpm.best,_xlpm.matchlen,0))))}
B108: 46003 | C108: Invoice | D108: 89612 | E108: NATURA GARDEN CENTRE | F108: AT PETUNIA HYBRIDS POT 12CM | G108: 30 | H108: 26.95 | I108: 808.5 | J108: 808.5 | K108: {=_xlfn.LET(_xlpm.d,UPPER(TRIM(CLEAN(SUBSTITUTE(F108,CHAR(160)," ")))),_xlpm.keys,UPPER(TRIM(MAP!$B$2:$B$1000)),_xlpm.vals,MAP!$A$2:$A$1000,_xlpm.matchlen,IF(ISNUMBER(SEARCH(_xlpm.keys,_xlpm.d)),LEN(_xlpm.keys),0),_xlpm.best,MAX(_xlpm.matchlen),IF(_xlpm.best=0,"",INDEX(_xlpm.vals,MATCH(_xlpm.best,_xlpm.matchlen,0))))} -> 12CM PETUNIA HYBRIDS
B109: 46008 | C109: Invoice | D109: 89644 | E109: BUILDERS WAREHOUSE:CENTURION | F109: AT PETUNIA HYBRIDS POT 12CM | G109: 50 | H109: 27.95 | I109: 1397.5 | J109: 2206 | K109: {=_xlfn.LET(_xlpm.d,UPPER(TRIM(CLEAN(SUBSTITUTE(F109,CHAR(160)," ")))),_xlpm.keys,UPPER(TRIM(MAP!$B$2:$B$1000)),_xlpm.vals,MAP!$A$2:$A$1000,_xlpm.matchlen,IF(ISNUMBER(SEARCH(_xlpm.keys,_xlpm.d)),LEN(_xlpm.keys),0),_xlpm.best,MAX(_xlpm.matchlen),IF(_xlpm.best=0,"",INDEX(_xlpm.vals,MATCH(_xlpm.best,_xlpm.matchlen,0))))} -> 12CM PETUNIA HYBRIDS
B110: 46008 | C110: Invoice | D110: 89645 | E110: BUILDERS WAREHOUSE:ZAMBEZI | F110: AT PETUNIA HYBRIDS POT 12CM | G110: 10 | H110: 27.95 | I110: 279.5 | J110: 2485.5 | K110: {=_xlfn.LET(_xlpm.d,UPPER(TRIM(CLEAN(SUBSTITUTE(F110,CHAR(160)," ")))),_xlpm.keys,UPPER(TRIM(MAP!$B$2:$B$1000)),_xlpm.vals,MAP!$A$2:$A$1000,_xlpm.matchlen,IF(ISNUMBER(SEARCH(_xlpm.keys,_xlpm.d)),LEN(_xlpm.keys),0),_xlpm.best,MAX(_xlpm.matchlen),IF(_xlpm.best=0,"",INDEX(_xlpm.vals,MATCH(_xlpm.best,_xlpm.matchlen,0))))} -> 12CM PETUNIA HYBRIDS
B111: 46009 | C111: Invoice | D111: 89661 | E111: BUILDERS WAREHOUSE:LAMBTON | F111: AT PETUNIA HYBRIDS POT 12CM | G111: 10 | H111: 27.95 | I111: 279.5 | J111: 2765 | K111: {=_xlfn.LET(_xlpm.d,UPPER(TRIM(CLEAN(SUBSTITUTE(F111,CHAR(160)," ")))),_xlpm.keys,UPPER(TRIM(MAP!$B$2:$B$1000)),_xlpm.vals,MAP!$A$2:$A$1000,_xlpm.matchlen,IF(ISNUMBER(SEARCH(_xlpm.keys,_xlpm.d)),LEN(_xlpm.keys),0),_xlpm.best,MAX(_xlpm.matchlen),IF(_xlpm.best=0,"",INDEX(_xlpm.vals,MATCH(_xlpm.best,_xlpm.matchlen,0))))} -> 12CM PETUNIA HYBRIDS
B112: 46014 | C112: Invoice | D112: 89682 | E112: BUILDERS WAREHOUSE:ERASMUS PARK | F112: AT PETUNIA HYBRIDS POT 12CM | G112: 50 | H112: 27.95 | I112: 1397.5 | J112: 4162.5 | K112: {=_xlfn.LET(_xlpm.d,UPPER(TRIM(CLEAN(SUBSTITUTE(F112,CHAR(160)," ")))),_xlpm.keys,UPPER(TRIM(MAP!$B$2:$B$1000)),_xlpm.vals,MAP!$A$2:$A$1000,_xlpm.matchlen,IF(ISNUMBER(SEARCH(_xlpm.keys,_xlpm.d)),LEN(_xlpm.keys),0),_xlpm.best,MAX(_xlpm.matchlen),IF(_xlpm.best=0,"",INDEX(_xlpm.vals,MATCH(_xlpm.best,_xlpm.matchlen,0))))} -> 12CM PETUNIA HYBRIDS
B113: 46015 | C113: Invoice | D113: 89714 | E113: BUILDERS WAREHOUSE:KLERKSDORP | F113: AT PETUNIA HYBRIDS POT 12CM | G113: 20 | H113: 27.95 | I113: 559 | J113: 4721.5 | K113: {=_xlfn.LET(_xlpm.d,UPPER(TRIM(CLEAN(SUBSTITUTE(F113,CHAR(160)," ")))),_xlpm.keys,UPPER(TRIM(MAP!$B$2:$B$1000)),_xlpm.vals,MAP!$A$2:$A$1000,_xlpm.matchlen,IF(ISNUMBER(SEARCH(_xlpm.keys,_xlpm.d)),LEN(_xlpm.keys),0),_xlpm.best,MAX(_xlpm.matchlen),IF(_xlpm.best=0,"",INDEX(_xlpm.vals,MATCH(_xlpm.best,_xlpm.matchlen,0))))} -> 12CM PETUNIA HYBRIDS
B114: 46015 | C114: Invoice | D114: 89715 | E114: BUILDERS WAREHOUSE:FLORIDA GLEN | F114: AT PETUNIA HYBRIDS POT 12CM | G114: 25 | H114: 27.95 | I114: 698.75 | J114: 5420.25 | K114: {=_xlfn.LET(_xlpm.d,UPPER(TRIM(CLEAN(SUBSTITUTE(F114,CHAR(160)," ")))),_xlpm.keys,UPPER(TRIM(MAP!$B$2:$B$1000)),_xlpm.vals,MAP!$A$2:$A$1000,_xlpm.matchlen,IF(ISNUMBER(SEARCH(_xlpm.keys,_xlpm.d)),LEN(_xlpm.keys),0),_xlpm.best,MAX(_xlpm.matchlen),IF(_xlpm.best=0,"",INDEX(_xlpm.vals,MATCH(_xlpm.best,_xlpm.matchlen,0))))} -> 12CM PETUNIA HYBRIDS
B115: 46021 | C115: Invoice | D115: 89734 | E115: BUILDERS WAREHOUSE:ZAMBEZI | F115: AT PETUNIA HYBRIDS POT 12CM | G115: 50 | H115: 27.95 | I115: 1397.5 | J115: 6817.75 | K115: {=_xlfn.LET(_xlpm.d,UPPER(TRIM(CLEAN(SUBSTITUTE(F115,CHAR(160)," ")))),_xlpm.keys,UPPER(TRIM(MAP!$B$2:$B$1000)),_xlpm.vals,MAP!$A$2:$A$1000,_xlpm.matchlen,IF(ISNUMBER(SEARCH(_xlpm.keys,_xlpm.d)),LEN(_xlpm.keys),0),_xlpm.best,MAX(_xlpm.matchlen),IF(_xlpm.best=0,"",INDEX(_xlpm.vals,MATCH(_xlpm.best,_xlpm.matchlen,0))))} -> 12CM PETUNIA HYBRIDS
B116: 46022 | C116: Invoice | D116: 89756 | E116: ECKARDS GARDEN PAVILION | F116: AT PETUNIA HYBRIDS POT 12CM | G116: 20 | H116: 26.95 | I116: 539 | J116: 7356.75 | K116: {=_xlfn.LET(_xlpm.d,UPPER(TRIM(CLEAN(SUBSTITUTE(F116,CHAR(160)," ")))),_xlpm.keys,UPPER(TRIM(MAP!$B$2:$B$1000)),_xlpm.vals,MAP!$A$2:$A$1000,_xlpm.matchlen,IF(ISNUMBER(SEARCH(_xlpm.keys,_xlpm.d)),LEN(_xlpm.keys),0),_xlpm.best,MAX(_xlpm.matchlen),IF(_xlpm.best=0,"",INDEX(_xlpm.vals,MATCH(_xlpm.best,_xlpm.matchlen,0))))} -> 12CM PETUNIA HYBRIDS
B117: 46027 | C117: Invoice | D117: 89764 | E117: BUILDERS WAREHOUSE:NEWMARKET | F117: AT PETUNIA HYBRIDS POT 12CM | G117: 50 | H117: 27.95 | I117: 1397.5 | J117: 8754.25 | K117: {=_xlfn.LET(_xlpm.d,UPPER(TRIM(CLEAN(SUBSTITUTE(F117,CHAR(160)," ")))),_xlpm.keys,UPPER(TRIM(MAP!$B$2:$B$1000)),_xlpm.vals,MAP!$A$2:$A$1000,_xlpm.matchlen,IF(ISNUMBER(SEARCH(_xlpm.keys,_xlpm.d)),LEN(_xlpm.keys),0),_xlpm.best,MAX(_xlpm.matchlen),IF(_xlpm.best=0,"",INDEX(_xlpm.vals,MATCH(_xlpm.best,_xlpm.matchlen,0))))} -> 12CM PETUNIA HYBRIDS
B118: 46028 | C118: Invoice | D118: 89772 | E118: BUILDERS WAREHOUSE:SILVERLAKES | F118: AT PETUNIA HYBRIDS POT 12CM | G118: 50 | H118: 27.95 | I118: 1397.5 | J118: 10151.75 | K118: {=_xlfn.LET(_xlpm.d,UPPER(TRIM(CLEAN(SUBSTITUTE(F118,CHAR(160)," ")))),_xlpm.keys,UPPER(TRIM(MAP!$B$2:$B$1000)),_xlpm.vals,MAP!$A$2:$A$1000,_xlpm.matchlen,IF(ISNUMBER(SEARCH(_xlpm.keys,_xlpm.d)),LEN(_xlpm.keys),0),_xlpm.best,MAX(_xlpm.matchlen),IF(_xlpm.best=0,"",INDEX(_xlpm.vals,MATCH(_xlpm.best,_xlpm.matchlen,0))))} -> 12CM PETUNIA HYBRIDS
B119: 46028 | C119: Invoice | D119: 89773 | E119: BUILDERS WAREHOUSE:LYNNWOOD | F119: AT PETUNIA HYBRIDS POT 12CM | G119: 25 | H119: 27.95 | I119: 698.75 | J119: 10850.5 | K119: {=_xlfn.LET(_xlpm.d,UPPER(TRIM(CLEAN(SUBSTITUTE(F119,CHAR(160)," ")))),_xlpm.keys,UPPER(TRIM(MAP!$B$2:$B$1000)),_xlpm.vals,MAP!$A$2:$A$1000,_xlpm.matchlen,IF(ISNUMBER(SEARCH(_xlpm.keys,_xlpm.d)),LEN(_xlpm.keys),0),_xlpm.best,MAX(_xlpm.matchlen),IF(_xlpm.best=0,"",INDEX(_xlpm.vals,MATCH(_xlpm.best,_xlpm.matchlen,0))))} -> 12CM PETUNIA HYBRIDS
... B152: 46112 | C152: Invoice | D152: 90605 | E152: BUILDERS WAREHOUSE:CEDAR SQUARE | F152: AT PETUNIA HYBRIDS POT 12CM | G152: 20 | H152: 27.95 | I152: 559 | J152: 51126.45 | K152: {=_xlfn.LET(_xlpm.d,UPPER(TRIM(CLEAN(SUBSTITUTE(F152,CHAR(160)," ")))),_xlpm.keys,UPPER(TRIM(MAP!$B$2:$B$1000)),_xlpm.vals,MAP!$A$2:$A$1000,_xlpm.matchlen,IF(ISNUMBER(SEARCH(_xlpm.keys,_xlpm.d)),LEN(_xlpm.keys),0),_xlpm.best,MAX(_xlpm.matchlen),IF(_xlpm.best=0,"",INDEX(_xlpm.vals,MATCH(_xlpm.best,_xlpm.matchlen,0))))} -> 12CM PETUNIA HYBRIDS
A153: Total for AT PETUNIA HYBRIDS POT 12CM | G153: 1831 | I153: =I108+I109+I110+I111+I112+I113+I114+I115+I116+I117+I118+I119+I120+I121+I122+I123+I124+I125+I126+I127+I128+I129+I130+I131+I132+I133+I134+I135+I136+I137+I138+I139+I140+I141+I142+I143+I144+I145+I146+I147+I148+I149+I150+I151+I152 -> 51126.45 | K153: {=_xlfn.LET(_xlpm.d,UPPER(TRIM(CLEAN(SUBSTITUTE(F153,CHAR(160)," ")))),_xlpm.keys,UPPER(TRIM(MAP!$B$2:$B$1000)),_xlpm.vals,MAP!$A$2:$A$1000,_xlpm.matchlen,IF(ISNUMBER(SEARCH(_xlpm.keys,_xlpm.d)),LEN(_xlpm.keys),0),_xlpm.best,MAX(_xlpm.matchlen),IF(_xlpm.best=0,"",INDEX(_xlpm.vals,MATCH(_xlpm.best,_xlpm.matchlen,0))))}
A154: AT PORTULACA POT 12CM | K154: {=_xlfn.LET(_xlpm.d,UPPER(TRIM(CLEAN(SUBSTITUTE(F154,CHAR(160)," ")))),_xlpm.keys,UPPER(TRIM(MAP!$B$2:$B$1000)),_xlpm.vals,MAP!$A$2:$A$1000,_xlpm.matchlen,IF(ISNUMBER(SEARCH(_xlpm.keys,_xlpm.d)),LEN(_xlpm.keys),0),_xlpm.best,MAX(_xlpm.matchlen),IF(_xlpm.best=0,"",INDEX(_xlpm.vals,MATCH(_xlpm.best,_xlpm.matchlen,0))))}
B155: 46085 | C155: Invoice | D155: 90359 | E155: FLORICULTURE WHOLESALE GROWERS | F155: PORTULACA POT 12CM | G155: 20 | H155: 21.2 | I155: 424 | J155: 424 | K155: {=_xlfn.LET(_xlpm.d,UPPER(TRIM(CLEAN(SUBSTITUTE(F155,CHAR(160)," ")))),_xlpm.keys,UPPER(TRIM(MAP!$B$2:$B$1000)),_xlpm.vals,MAP!$A$2:$A$1000,_xlpm.matchlen,IF(ISNUMBER(SEARCH(_xlpm.keys,_xlpm.d)),LEN(_xlpm.keys),0),_xlpm.best,MAX(_xlpm.matchlen),IF(_xlpm.best=0,"",INDEX(_xlpm.vals,MATCH(_xlpm.best,_xlpm.matchlen,0))))} -> 12CM COLOUR POT
B156: 46100 | C156: Invoice | D156: 90496 | E156: LITTLE AUSTRIA | F156: AT PORTULACA POT 12CM (SPECIAL) | G156: 30 | H156: 8.9 | I156: 267 | J156: 691 | K156: {=_xlfn.LET(_xlpm.d,UPPER(TRIM(CLEAN(SUBSTITUTE(F156,CHAR(160)," ")))),_xlpm.keys,UPPER(TRIM(MAP!$B$2:$B$1000)),_xlpm.vals,MAP!$A$2:$A$1000,_xlpm.matchlen,IF(ISNUMBER(SEARCH(_xlpm.keys,_xlpm.d)),LEN(_xlpm.keys),0),_xlpm.best,MAX(_xlpm.matchlen),IF(_xlpm.best=0,"",INDEX(_xlpm.vals,MATCH(_xlpm.best,_xlpm.matchlen,0))))} -> 12CM COLOUR POT
B157: 46104 | C157: Invoice | D157: 90513 | E157: BUILDERS WAREHOUSE:ZAMBEZI | F157: AT PORTULACA POT 12CM | G157: 50 | H157: 0 | I157: 0 | J157: 691 | K157: {=_xlfn.LET(_xlpm.d,UPPER(TRIM(CLEAN(SUBSTITUTE(F157,CHAR(160)," ")))),_xlpm.keys,UPPER(TRIM(MAP!$B$2:$B$1000)),_xlpm.vals,MAP!$A$2:$A$1000,_xlpm.matchlen,IF(ISNUMBER(SEARCH(_xlpm.keys,_xlpm.d)),LEN(_xlpm.keys),0),_xlpm.best,MAX(_xlpm.matchlen),IF(_xlpm.best=0,"",INDEX(_xlpm.vals,MATCH(_xlpm.best,_xlpm.matchlen,0))))} -> 12CM COLOUR POT
A158: Total for AT PORTULACA POT 12CM | G158: 100 | I158: =I155+I156+I157 -> 691 | K158: {=_xlfn.LET(_xlpm.d,UPPER(TRIM(CLEAN(SUBSTITUTE(F158,CHAR(160)," ")))),_xlpm.keys,UPPER(TRIM(MAP!$B$2:$B$1000)),_xlpm.vals,MAP!$A$2:$A$1000,_xlpm.matchlen,IF(ISNUMBER(SEARCH(_xlpm.keys,_xlpm.d)),LEN(_xlpm.keys),0),_xlpm.best,MAX(_xlpm.matchlen),IF(_xlpm.best=0,"",INDEX(_xlpm.vals,MATCH(_xlpm.best,_xlpm.matchlen,0))))}
A159: AT SALVIA POT 12CM | K159: {=_xlfn.LET(_xlpm.d,UPPER(TRIM(CLEAN(SUBSTITUTE(F159,CHAR(160)," ")))),_xlpm.keys,UPPER(TRIM(MAP!$B$2:$B$1000)),_xlpm.vals,MAP!$A$2:$A$1000,_xlpm.matchlen,IF(ISNUMBER(SEARCH(_xlpm.keys,_xlpm.d)),LEN(_xlpm.keys),0),_xlpm.best,MAX(_xlpm.matchlen),IF(_xlpm.best=0,"",INDEX(_xlpm.vals,MATCH(_xlpm.best,_xlpm.matchlen,0))))}
B160: 46066 | C160: Invoice | D160: 90193 | E160: THYME SQUARE | F160: AT SALVIA POT 12CM | G160: 20 | H160: 11.95 | I160: 239 | J160: 239 | K160: {=_xlfn.LET(_xlpm.d,UPPER(TRIM(CLEAN(SUBSTITUTE(F160,CHAR(160)," ")))),_xlpm.keys,UPPER(TRIM(MAP!$B$2:$B$1000)),_xlpm.vals,MAP!$A$2:$A$1000,_xlpm.matchlen,IF(ISNUMBER(SEARCH(_xlpm.keys,_xlpm.d)),LEN(_xlpm.keys),0),_xlpm.best,MAX(_xlpm.matchlen),IF(_xlpm.best=0,"",INDEX(_xlpm.vals,MATCH(_xlpm.best,_xlpm.matchlen,0))))} -> 12CM COLOUR POT
B161: 46070 | C161: Invoice | D161: 90205 | E161: BUILDERS WAREHOUSE:GEZINA NEW | F161: AT SALVIA POT 12CM | G161: 25 | H161: 12.2 | I161: 305 | J161: 544 | K161: {=_xlfn.LET(_xlpm.d,UPPER(TRIM(CLEAN(SUBSTITUTE(F161,CHAR(160)," ")))),_xlpm.keys,UPPER(TRIM(MAP!$B$2:$B$1000)),_xlpm.vals,MAP!$A$2:$A$1000,_xlpm.matchlen,IF(ISNUMBER(SEARCH(_xlpm.keys,_xlpm.d)),LEN(_xlpm.keys),0),_xlpm.best,MAX(_xlpm.matchlen),IF(_xlpm.best=0,"",INDEX(_xlpm.vals,MATCH(_xlpm.best,_xlpm.matchlen,0))))} -> 12CM COLOUR POT
B162: 46073 | C162: Invoice | D162: 90247 | E162: THYME SQUARE | F162: AT SALVIA POT 12CM | G162: 10 | H162: 11.95 | I162: 119.5 | J162: 663.5 | K162: {=_xlfn.LET(_xlpm.d,UPPER(TRIM(CLEAN(SUBSTITUTE(F162,CHAR(160)," ")))),_xlpm.keys,UPPER(TRIM(MAP!$B$2:$B$1000)),_xlpm.vals,MAP!$A$2:$A$1000,_xlpm.matchlen,IF(ISNUMBER(SEARCH(_xlpm.keys,_xlpm.d)),LEN(_xlpm.keys),0),_xlpm.best,MAX(_xlpm.matchlen),IF(_xlpm.best=0,"",INDEX(_xlpm.vals,MATCH(_xlpm.best,_xlpm.matchlen,0))))} -> 12CM COLOUR POT
B163: 46079 | C163: Invoice | D163: 90293 | E163: LITTLE AUSTRIA | F163: AT SALVIA POT 12CM (Special) | G163: 40 | H163: 8.99 | I163: 359.6 | J163: 1023.1 | K163: {=_xlfn.LET(_xlpm.d,UPPER(TRIM(CLEAN(SUBSTITUTE(F163,CHAR(160)," ")))),_xlpm.keys,UPPER(TRIM(MAP!$B$2:$B$1000)),_xlpm.vals,MAP!$A$2:$A$1000,_xlpm.matchlen,IF(ISNUMBER(SEARCH(_xlpm.keys,_xlpm.d)),LEN(_xlpm.keys),0),_xlpm.best,MAX(_xlpm.matchlen),IF(_xlpm.best=0,"",INDEX(_xlpm.vals,MATCH(_xlpm.best,_xlpm.matchlen,0))))} -> 12CM COLOUR POT
B164: 46080 | C164: Invoice | D164: 90305 | E164: THYME SQUARE | F164: AT SALVIA POT 12CM | G164: 10 | H164: 11.95 | I164: 119.5 | J164: 1142.6 | K164: {=_xlfn.LET(_xlpm.d,UPPER(TRIM(CLEAN(SUBSTITUTE(F164,CHAR(160)," ")))),_xlpm.keys,UPPER(TRIM(MAP!$B$2:$B$1000)),_xlpm.vals,MAP!$A$2:$A$1000,_xlpm.matchlen,IF(ISNUMBER(SEARCH(_xlpm.keys,_xlpm.d)),LEN(_xlpm.keys),0),_xlpm.best,MAX(_xlpm.matchlen),IF(_xlpm.best=0,"",INDEX(_xlpm.vals,MATCH(_xlpm.best,_xlpm.matchlen,0))))} -> 12CM COLOUR POT
B165: 46086 | C165: Invoice | D165: 90371 | E165: GARDENSHOP PARKTOWN | F165: AT SALVIA POT 12CM (SPECIAL) | G165: 10 | H165: 8.99 | I165: 89.9 | J165: 1232.5 | K165: {=_xlfn.LET(_xlpm.d,UPPER(TRIM(CLEAN(SUBSTITUTE(F165,CHAR(160)," ")))),_xlpm.keys,UPPER(TRIM(MAP!$B$2:$B$1000)),_xlpm.vals,MAP!$A$2:$A$1000,_xlpm.matchlen,IF(ISNUMBER(SEARCH(_xlpm.keys,_xlpm.d)),LEN(_xlpm.keys),0),_xlpm.best,MAX(_xlpm.matchlen),IF(_xlpm.best=0,"",INDEX(_xlpm.vals,MATCH(_xlpm.best,_xlpm.matchlen,0))))} -> 12CM COLOUR POT
A166: Total for AT SALVIA POT 12CM | G166: 115 | I166: =I160+I161+I162+I163+I164+I165 -> 1232.5 | K166: {=_xlfn.LET(_xlpm.d,UPPER(TRIM(CLEAN(SUBSTITUTE(F166,CHAR(160)," ")))),_xlpm.keys,UPPER(TRIM(MAP!$B$2:$B$1000)),_xlpm.vals,MAP!$A$2:$A$1000,_xlpm.matchlen,IF(ISNUMBER(SEARCH(_xlpm.keys,_xlpm.d)),LEN(_xlpm.keys),0),_xlpm.best,MAX(_xlpm.matchlen),IF(_xlpm.best=0,"",INDEX(_xlpm.vals,MATCH(_xlpm.best,_xlpm.matchlen,0))))}
A167: AT SEASONAL COLOUR 12CM POT | K167: {=_xlfn.LET(_xlpm.d,UPPER(TRIM(CLEAN(SUBSTITUTE(F167,CHAR(160)," ")))),_xlpm.keys,UPPER(TRIM(MAP!$B$2:$B$1000)),_xlpm.vals,MAP!$A$2:$A$1000,_xlpm.matchlen,IF(ISNUMBER(SEARCH(_xlpm.keys,_xlpm.d)),LEN(_xlpm.keys),0),_xlpm.best,MAX(_xlpm.matchlen),IF(_xlpm.best=0,"",INDEX(_xlpm.vals,MATCH(_xlpm.best,_xlpm.matchlen,0))))}
B168: 45982 | C168: Invoice | D168: 89294 | E168: BUILDERS WAREHOUSE:RIVONIA | F168: AT SEASONAL COLOUR 12CM POT | G168: 300 | H168: 7 | I168: 2100 | J168: 2100 | K168: {=_xlfn.LET(_xlpm.d,UPPER(TRIM(CLEAN(SUBSTITUTE(F168,CHAR(160)," ")))),_xlpm.keys,UPPER(TRIM(MAP!$B$2:$B$1000)),_xlpm.vals,MAP!$A$2:$A$1000,_xlpm.matchlen,IF(ISNUMBER(SEARCH(_xlpm.keys,_xlpm.d)),LEN(_xlpm.keys),0),_xlpm.best,MAX(_xlpm.matchlen),IF(_xlpm.best=0,"",INDEX(_xlpm.vals,MATCH(_xlpm.best,_xlpm.matchlen,0))))} -> 12CM COLOUR POT
B169: 45982 | C169: Invoice | D169: 89295 | E169: BUILDERS WAREHOUSE:NELSPRUIT | F169: AT SEASONAL COLOUR 12CM POT | G169: 300 | H169: 7 | I169: 2100 | J169: 4200 | K169: {=_xlfn.LET(_xlpm.d,UPPER(TRIM(CLEAN(SUBSTITUTE(F169,CHAR(160)," ")))),_xlpm.keys,UPPER(TRIM(MAP!$B$2:$B$1000)),_xlpm.vals,MAP!$A$2:$A$1000,_xlpm.matchlen,IF(ISNUMBER(SEARCH(_xlpm.keys,_xlpm.d)),LEN(_xlpm.keys),0),_xlpm.best,MAX(_xlpm.matchlen),IF(_xlpm.best=0,"",INDEX(_xlpm.vals,MATCH(_xlpm.best,_xlpm.matchlen,0))))} -> 12CM COLOUR POT
B170: 45982 | C170: Invoice | D170: 89296 | E170: BUILDERS WAREHOUSE:BLOEMFONTEIN | F170: AT SEASONAL COLOUR 12CM POT | G170: 500 | H170: 7 | I170: 3500 | J170: 7700 | K170: {=_xlfn.LET(_xlpm.d,UPPER(TRIM(CLEAN(SUBSTITUTE(F170,CHAR(160)," ")))),_xlpm.keys,UPPER(TRIM(MAP!$B$2:$B$1000)),_xlpm.vals,MAP!$A$2:$A$1000,_xlpm.matchlen,IF(ISNUMBER(SEARCH(_xlpm.keys,_xlpm.d)),LEN(_xlpm.keys),0),_xlpm.best,MAX(_xlpm.matchlen),IF(_xlpm.best=0,"",INDEX(_xlpm.vals,MATCH(_xlpm.best,_xlpm.matchlen,0))))} -> 12CM COLOUR POT
B171: 45982 | C171: Invoice | D171: 89297 | E171: BUILDERS WAREHOUSE:BAOBAB | F171: AT SEASONAL COLOUR 12CM POT | G171: 80 | H171: 7 | I171: 560 | J171: 8260 | K171: {=_xlfn.LET(_xlpm.d,UPPER(TRIM(CLEAN(SUBSTITUTE(F171,CHAR(160)," ")))),_xlpm.keys,UPPER(TRIM(MAP!$B$2:$B$1000)),_xlpm.vals,MAP!$A$2:$A$1000,_xlpm.matchlen,IF(ISNUMBER(SEARCH(_xlpm.keys,_xlpm.d)),LEN(_xlpm.keys),0),_xlpm.best,MAX(_xlpm.matchlen),IF(_xlpm.best=0,"",INDEX(_xlpm.vals,MATCH(_xlpm.best,_xlpm.matchlen,0))))} -> 12CM COLOUR POT
B172: 45982 | C172: Invoice | D172: 89298 | E172: BUILDERS WAREHOUSE:POLOKWANE | F172: AT SEASONAL COLOUR 12CM POT | G172: 150 | H172: 7 | I172: 1050 | J172: 9310 | K172: {=_xlfn.LET(_xlpm.d,UPPER(TRIM(CLEAN(SUBSTITUTE(F172,CHAR(160)," ")))),_xlpm.keys,UPPER(TRIM(MAP!$B$2:$B$1000)),_xlpm.vals,MAP!$A$2:$A$1000,_xlpm.matchlen,IF(ISNUMBER(SEARCH(_xlpm.keys,_xlpm.d)),LEN(_xlpm.keys),0),_xlpm.best,MAX(_xlpm.matchlen),IF(_xlpm.best=0,"",INDEX(_xlpm.vals,MATCH(_xlpm.best,_xlpm.matchlen,0))))} -> 12CM COLOUR POT
B173: 45982 | C173: Invoice | D173: 89301 | E173: BUILDERS WAREHOUSE:RUSTENBURG | F173: AT SEASONAL COLOUR 12CM POT | G173: 300 | H173: 7 | I173: 2100 | J173: 11410 | K173: {=_xlfn.LET(_xlpm.d,UPPER(TRIM(CLEAN(SUBSTITUTE(F173,CHAR(160)," ")))),_xlpm.keys,UPPER(TRIM(MAP!$B$2:$B$1000)),_xlpm.vals,MAP!$A$2:$A$1000,_xlpm.matchlen,IF(ISNUMBER(SEARCH(_xlpm.keys,_xlpm.d)),LEN(_xlpm.keys),0),_xlpm.best,MAX(_xlpm.matchlen),IF(_xlpm.best=0,"",INDEX(_xlpm.vals,MATCH(_xlpm.best,_xlpm.matchlen,0))))} -> 12CM COLOUR POT
B174: 45982 | C174: Invoice | D174: 89302 | E174: BUILDERS WAREHOUSE:CEDAR SQUARE | F174: AT SEASONAL COLOUR 12CM POT | G174: 150 | H174: 7 | I174: 1050 | J174: 12460 | K174: {=_xlfn.LET(_xlpm.d,UPPER(TRIM(CLEAN(SUBSTITUTE(F174,CHAR(160)," ")))),_xlpm.keys,UPPER(TRIM(MAP!$B$2:$B$1000)),_xlpm.vals,MAP!$A$2:$A$1000,_xlpm.matchlen,IF(ISNUMBER(SEARCH(_xlpm.keys,_xlpm.d)),LEN(_xlpm.keys),0),_xlpm.best,MAX(_xlpm.matchlen),IF(_xlpm.best=0,"",INDEX(_xlpm.vals,MATCH(_xlpm.best,_xlpm.matchlen,0))))} -> 12CM COLOUR POT
B175: 45982 | C175: Invoice | D175: 89303 | E175: BUILDERS WAREHOUSE:FOURWAYS | F175: AT SEASONAL COLOUR 12CM POT | G175: 100 | H175: 7 | I175: 700 | J175: 13160 | K175: {=_xlfn.LET(_xlpm.d,UPPER(TRIM(CLEAN(SUBSTITUTE(F175,CHAR(160)," ")))),_xlpm.keys,UPPER(TRIM(MAP!$B$2:$B$1000)),_xlpm.vals,MAP!$A$2:$A$1000,_xlpm.matchlen,IF(ISNUMBER(SEARCH(_xlpm.keys,_xlpm.d)),LEN(_xlpm.keys),0),_xlpm.best,MAX(_xlpm.matchlen),IF(_xlpm.best=0,"",INDEX(_xlpm.vals,MATCH(_xlpm.best,_xlpm.matchlen,0))))} -> 12CM COLOUR POT
B176: 45982 | C176: Invoice | D176: 89304 | E176: BUILDERS WAREHOUSE:GLEN EAGLES | F176: AT SEASONAL COLOUR 12CM POT | G176: 200 | H176: 7 | I176: 1400 | J176: 14560 | K176: {=_xlfn.LET(_xlpm.d,UPPER(TRIM(CLEAN(SUBSTITUTE(F176,CHAR(160)," ")))),_xlpm.keys,UPPER(TRIM(MAP!$B$2:$B$1000)),_xlpm.vals,MAP!$A$2:$A$1000,_xlpm.matchlen,IF(ISNUMBER(SEARCH(_xlpm.keys,_xlpm.d)),LEN(_xlpm.keys),0),_xlpm.best,MAX(_xlpm.matchlen),IF(_xlpm.best=0,"",INDEX(_xlpm.vals,MATCH(_xlpm.best,_xlpm.matchlen,0))))} -> 12CM COLOUR POT
...

Sheet MAP
A1: 12CM COLOUR POT | B1: AT SEASONAL COLOUR 12CM POT | E1: SEEDLINGS
A2: 12CM COLOUR POT | B2: CELOSIA 12CM | E2: 15CM COLOUR POTS
A3: 12CM COLOUR POT | B3: AT HYPOESTES POT 12CM 850040155 | E3: 12CM COLOUR POT
A4: 12CM COLOUR POT | B4: AT IMPATIENS POT 12CM 850040109 | E4: 12CM HERB
A5: 12CM COLOUR POT | B5: COLOUR MAGIC 12CM | E5: PETUNIA HYBRIDS
A6: 12CM COLOUR POT | B6: PETUNIA 12CM | E6: PLANT TO PLATE
A7: 12CM PRIMROSE/OBCONICA | B7: PRIMROSE | E7: SIMPLY BEAUTIFUL
A8: 12CM COLOUR POT | B8: VINCA VICTORY GRAPE | E8: MID RANGE
A9: 12CM COLOUR POT | B9: FLOWER POT 12CM | E9: CALIBRACHOA
A10: 12CM HERB/VEG | B10: BASIL | E10: 20CM AERO BOWL
A11: 12CM HERB/VEG | B11: CHIVES | E11: 14CM SUCCULENTS
A12: 12CM HERB/VEG | B12: CORIANDER | E12: 25CM HANGING BASKET
... A24: 12CM HERB/VEG | B24: HERB L/STYLE | E24: CHILLI POT
A25: 12CM ORNAMENTAL CHILLI | B25: ORNAMENTAL CHILLI
A26: 12CM ORNAMENTAL CHILLI | B26: CHILLI ORNAMENTAL
A27: 12CM PATIO RANGE | B27: CALCEOLARIA | E27: LAWN PLUGS
A28: 12CM PATIO RANGE | B28: CINERARIA | E28: 12CM GRASS POTS
A29: 12CM PATIO RANGE | B29: CYCLAMEN | E29: 17CM GERANIUM
A30: 15CM COLOUR POTS | B30: PELARGONIUM
A31: 15CM COLOUR POTS | B31: ALYSSUM CLEAR CRYSTAL
A32: 15CM COLOUR POTS | B32: ANTIRRHINUM
A33: 15CM COLOUR POTS | B33: DIANTHUS
A34: 15CM COLOUR POTS | B34: CELOSIA DRACULA
A35: 15CM COLOUR POTS | B35: COLOUR MAGIC 15CM
A36: 15CM COLOUR POTS | B36: COLOUR MAGIC ALYSSUM
A37: 15CM COLOUR POTS | B37: COLOUR MAGIC BELLIS
A38: 15CM COLOUR POTS | B38: COLOUR MAGIC CALENDULA
A39: 15CM COLOUR POTS | B39: COLOUR MAGIC DIANTHUS
A40: 15CM COLOUR POTS | B40: COLOUR MAGIC GAZANIA
A41: 15CM COLOUR POTS | B41: COLOUR MAGIC GYPSOPHILLA
... A109: COLOUR PLUGS 48 | B109: COLOUR PLUGS 48
A110: SEEDLINGS | B110: 28884
A111: SEEDLINGS | B111: SEEDLING FLOWER 6 PACK
A112: SEEDLINGS | B112: SEEDLING VEGETABLE 6 PACK
A113: SEEDLINGS | B113: VEGETABLE SEEDLINGS 6 PACK
A114: 9CM SUCCULENTS | B114: COLOUR MAGIC 9CM
A115: 9CM SUCCULENTS | B115: ECHEVERIA SET OLIVER
A116: 9CM SUCCULENTS | B116: SUCCULENT 9CM
A117: ADVERTISING | B117: ADVERTISING
A118: BUILDERS REBATE | B118: BUILDERS REBATE
A119: D&H | B119: D&H
A120: DISCOUNT | B120: DISCOUNT
A121: CALIBRACHOA | B121: FLORA SELECT MINI PETUNIA
A122: 17CM BEGONIA | B122: FLORA SELECT BEGONIA
... A751: LAWN PLUGS | B751: L/M GRASS 128 PACK

Sheet TABLE
A1: Years (Date) | B1: 2026
A2: Months (Date) | B2: Apr
A3: Date | B3: (All)
A5: Row Labels | B5: Sum of Quantity | C5: Percentage
A6: 128 COLOUR PLUGS | B6: 10 | C6: 0.00013505301
A7: 12CM COLOUR POT | B7: 2521 | C7: 0.034046863
A8: 12CM GRASS POTS | B8: 6 | C8: 8.1031805e-05
A9: 12CM HERB/VEG | B9: 2932 | C9: 0.039597542
A10: 12CM ORNAMENTAL CHILLI | B10: 50 | C10: 0.00067526504
A11: 12CM PATIO RANGE | B11: 14 | C11: 0.00018907421
A12: 14CM SUCCULENTS | B12: 49 | C12: 0.00066175974
A13: 15CM ANGELONIA | B13: 38 | C13: 0.00051320143
A14: 15CM COLOUR POTS | B14: 11389 | C14: 0.15381187
A15: 20CM AERO BOWL | B15: 833 | C15: 0.011249916
A16: 24 PACKS | B16: 134 | C16: 0.0018097103
A17: 25CM COLOUR POT | B17: 519 | C17: 0.0070092511
... A32: Grand Total | B32: 74045 | C32: 1
